[
  {
    "mint_account": "H1C1XUXSMR4Q5CpsX8cMeawbq2cBkw28XcdMMS8LN9yk",
    "new_uri": "https://dup-in-isolate.s3.us-west-1.amazonaws.com/1-lock.json"
  },
  {
    "mint_account": "76ME7xWes2SYrGJqu3nRWuvy25fh4WHeytHiaXuQ1A6R",
    "new_uri": "https://dup-in-isolate.s3.us-west-1.amazonaws.com/1-lock.json"
  },
  {
    "mint_account": "FEsdrcqCbfzrEkUC5FMa3jzyKD72bijHHrmMkXjPTeJa",
    "new_uri": "https://dup-in-isolate.s3.us-west-1.amazonaws.com/2-lock.json"
  },
  {
    "mint_account": "BE7RVKM64zziTDGkbP1JKrMMKPwjkn9oHAatfK3535aP",
    "new_uri": "https://dup-in-isolate.s3.us-west-1.amazonaws.com/2-lock.json"
  },
  {
    "mint_account": "AEKBbh3ECQH4BjBttqM8RoS75mm7NoNibso4drwa59HC",
    "new_uri": "https://dup-in-isolate.s3.us-west-1.amazonaws.com/3953-lock.json"
  },
  {
    "mint_account": "FNExxne5BfxYJyRrXEouU9oHeM7o48RyDUKx735BGVwP",
    "new_uri": "https://dup-in-isolate.s3.us-west-1.amazonaws.com/3600-lock.json"
  },
  {
    "mint_account": "3dVe8FrogDtDfe81Um9trysxaPW9ojpxtHPyziy9VDms",
    "new_uri": "https://dup-in-isolate.s3.us-west-1.amazonaws.com/3871-lock.json"
  },
  {
    "mint_account": "rrxrKksTXLMD9Yp65Yjf1cbcKr3qJmkuuraT6DzCqyr",
    "new_uri": "https://dup-in-isolate.s3.us-west-1.amazonaws.com/5-lock.json"
  },
  {
    "mint_account": "GxiKMZWRFwyDps21Yay1hQSnYtfg5HfYkEUeKv4nhriG",
    "new_uri": "https://dup-in-isolate.s3.us-west-1.amazonaws.com/5-lock.json"
  },
  {
    "mint_account": "GrhEixszPac4med6uXFyffpYMFgcezGoXJLQpbFm1k7o",
    "new_uri": "https://dup-in-isolate.s3.us-west-1.amazonaws.com/3-lock.json"
  },
  {
    "mint_account": "J1doYRzF1FRe7BxeqwVxyKFbfGnDjGfBRaaE5CMbF6SR",
    "new_uri": "https://dup-in-isolate.s3.us-west-1.amazonaws.com/3-lock.json"
  },
  {
    "mint_account": "gP8SQfGiUfCvbFMscBiFFse4uTzTRKVz5mGrTLXA2bz",
    "new_uri": "https://dup-in-isolate.s3.us-west-1.amazonaws.com/1708-lock.json"
  },
  {
    "mint_account": "BYemEJuazF4gZV7zLiDYpXgxRVyacT9ZMwr5piVBJ3F6",
    "new_uri": "https://dup-in-isolate.s3.us-west-1.amazonaws.com/1768-lock.json"
  },
  {
    "mint_account": "7n9YZMZuqi2qrJdd1tNW2oET9WqganCMMBnH8tSB68A2",
    "new_uri": "https://dup-in-isolate.s3.us-west-1.amazonaws.com/1795-lock.json"
  },
  {
    "mint_account": "FZYaSL5B2LJdXzyVcC8FU3GRqj818xp9yvDUy4Ta9qjy",
    "new_uri": "https://dup-in-isolate.s3.us-west-1.amazonaws.com/3717-lock.json"
  },
  {
    "mint_account": "f8WNenvskozDvszDyXZB3cs9JkRmFjwoW5QkBENQRqN",
    "new_uri": "https://dup-in-isolate.s3.us-west-1.amazonaws.com/3718-lock.json"
  },
  {
    "mint_account": "EH6cr2WVvFkuQ7cB9r4WcJm2kCbF7jeyZet9AWG6L8M2",
    "new_uri": "https://dup-in-isolate.s3.us-west-1.amazonaws.com/3749-lock.json"
  },
  {
    "mint_account": "7e2JXYpod7tCyWpjCehMdNwsEPsofht8uEcxYB3ooWhP",
    "new_uri": "https://dup-in-isolate.s3.us-west-1.amazonaws.com/0-lock.json"
  },
  {
    "mint_account": "EZ8qLuTVexHKEzeaNuxJc35Y6tTEYVgrd3WggRMnrjLp",
    "new_uri": "https://dup-in-isolate.s3.us-west-1.amazonaws.com/0-lock.json"
  },
  {
    "mint_account": "74RfLZXMQiYvQwRAoqB9B7ned7SXQUMdjAgfYCi3jr8Y",
    "new_uri": "https://dup-in-isolate.s3.us-west-1.amazonaws.com/4-lock.json"
  },
  {
    "mint_account": "55o6aJmntUXN9VQamk48ELGYSfXhz3sYLwCVb6b1v2LV",
    "new_uri": "https://dup-in-isolate.s3.us-west-1.amazonaws.com/4-lock.json"
  },
  {
    "mint_account": "GEBYGfQ73wFxiS5RVkY7xFea4tJB6GKwTqG7EM1A8qNM",
    "new_uri": "https://dup-in-isolate.s3.us-west-1.amazonaws.com/6-lock.json"
  },
  {
    "mint_account": "63s1PVDqncFMSg9nof6PuJg11VL4KDedZGUNoq4Z35Qw",
    "new_uri": "https://dup-in-isolate.s3.us-west-1.amazonaws.com/6-lock.json"
  },
  {
    "mint_account": "AbVQ2SmVY8bxxa1seN3BrGakhj6JQLQLj8kfFo4GiPQh",
    "new_uri": "https://dup-in-isolate.s3.us-west-1.amazonaws.com/7-lock.json"
  },
  {
    "mint_account": "CU5toETRBH8N3dDCGrt7w6Lt6e4T7QvyD7qdNKorqx7S",
    "new_uri": "https://dup-in-isolate.s3.us-west-1.amazonaws.com/7-lock.json"
  },
  {
    "mint_account": "8zo33AoQkDTJM9rvPT4tK3mfj59U4kHshMUiM4EcypWS",
    "new_uri": "https://dup-in-isolate.s3.us-west-1.amazonaws.com/115-lock.json"
  },
  {
    "mint_account": "HWNwsnFck9p4mdgLF13nu7ikwGZbJAVkw1CWWknrT9f4",
    "new_uri": "https://dup-in-isolate.s3.us-west-1.amazonaws.com/1712-lock.json"
  },
  {
    "mint_account": "DLiXFBKFXuQNsRmvDrDcctg5J51NrMp781nkVPmmLczK",
    "new_uri": "https://dup-in-isolate.s3.us-west-1.amazonaws.com/1739-lock.json"
  },
  {
    "mint_account": "CyPCi4D3Lh3wF9LeUYkjdxbZjiVa6v5nNdCZ6mAzg1K8",
    "new_uri": "https://dup-in-isolate.s3.us-west-1.amazonaws.com/1792-lock.json"
  },
  {
    "mint_account": "BE3PiFCitGKnuYYXRA6wWBN8N5fgRx3AeSJrd7V97qSJ",
    "new_uri": "https://dup-in-isolate.s3.us-west-1.amazonaws.com/3902-lock.json"
  },
  {
    "mint_account": "5q43uvNFuTJ5GF951STQGXgYnFCjv6LmFdgjwK8ZGEEz",
    "new_uri": "https://dup-in-isolate.s3.us-west-1.amazonaws.com/3921-lock.json"
  },
  {
    "mint_account": "Fg8sGP1AtaJYXzGfKAinmpePa55kCDuewfzFmxEJqmAd",
    "new_uri": "https://dup-in-isolate.s3.us-west-1.amazonaws.com/3588-lock.json"
  },
  {
    "mint_account": "CysxDkdZxiUXiQCuefKrPqR3jPx9tCdamPgJxzxEC9t1",
    "new_uri": "https://dup-in-isolate.s3.us-west-1.amazonaws.com/4012-lock.json"
  },
  {
    "mint_account": "EWwF3D2MhTeqa3ggkz4T96fXevWkub4RgsXVazQ9i3ap",
    "new_uri": "https://dup-in-isolate.s3.us-west-1.amazonaws.com/3684-lock.json"
  },
  {
    "mint_account": "EWBo2Mc5f8FU59oCqjQ6rhzLF6o3H1wXzZcU32ASmhBL",
    "new_uri": "https://dup-in-isolate.s3.us-west-1.amazonaws.com/4080-lock.json"
  },
  {
    "mint_account": "8TAEmGuVxZotbfwN9ihMdd1acDso3eidWeZGmJ9rYeKp",
    "new_uri": "https://dup-in-isolate.s3.us-west-1.amazonaws.com/4158-lock.json"
  },
  {
    "mint_account": "6wST8ZxCjNyZbgbgeQ85fBUPKDB7LEHfgddTxK3eMGpT",
    "new_uri": "https://dup-in-isolate.s3.us-west-1.amazonaws.com/3828-lock.json"
  },
  {
    "mint_account": "GdRUwCAnVYV4SrgkJ5P4QGu3vJUJD9wKKgX2hUGsSe3j",
    "new_uri": "https://dup-in-isolate.s3.us-west-1.amazonaws.com/9-lock.json"
  },
  {
    "mint_account": "HddHVCbnFimZqLa8DLNLHhmK539FN76vjXzVnSrgzRiq",
    "new_uri": "https://dup-in-isolate.s3.us-west-1.amazonaws.com/9-lock.json"
  },
  {
    "mint_account": "5GyccfmbTjAPPkzuAhPiH3BgwF4UWSxHcxTySy62SbcY",
    "new_uri": "https://dup-in-isolate.s3.us-west-1.amazonaws.com/8-lock.json"
  },
  {
    "mint_account": "DkdQfL2nMoTD5D7TSM71bf5iDaSRUpgztwiUM76uuWjD",
    "new_uri": "https://dup-in-isolate.s3.us-west-1.amazonaws.com/8-lock.json"
  },
  {
    "mint_account": "8cap8uF8K2dksr1rdSZPZ5VuckEDAmMMb2b9fnRYNt1Z",
    "new_uri": "https://dup-in-isolate.s3.us-west-1.amazonaws.com/10-lock.json"
  },
  {
    "mint_account": "BYVJ7KLMPd7XbptBptTgMx9fdarNQtGG5bPpdDhBJMwt",
    "new_uri": "https://dup-in-isolate.s3.us-west-1.amazonaws.com/10-lock.json"
  },
  {
    "mint_account": "9Y4oVBBiAMxHyJsMtsP7jKbEpgH5fA6LRktMVw3AKj58",
    "new_uri": "https://dup-in-isolate.s3.us-west-1.amazonaws.com/1636-lock.json"
  },
  {
    "mint_account": "HiYXhmLkt26is58nJfaLMccw3G8NfNE7cqXzqYX2LXvJ",
    "new_uri": "https://dup-in-isolate.s3.us-west-1.amazonaws.com/11-lock.json"
  },
  {
    "mint_account": "Fxwai5aQDNCJJxvLfT6yRhgPACZT4RtqJ8fGMEFHNpvT",
    "new_uri": "https://dup-in-isolate.s3.us-west-1.amazonaws.com/11-lock.json"
  },
  {
    "mint_account": "Cgq4wQtHL2sTjDuyJiX48sFnQkfdhv2tNTfZP7WQPtxQ",
    "new_uri": "https://dup-in-isolate.s3.us-west-1.amazonaws.com/4138-lock.json"
  },
  {
    "mint_account": "HicNGRTdB1yKgTnkCH1ZfTYow9SgMB7B3AXZq3hBHrkG",
    "new_uri": "https://dup-in-isolate.s3.us-west-1.amazonaws.com/4181-lock.json"
  },
  {
    "mint_account": "GNgHFDeXti4qc8wK4uhGTAqvZgMMv1uG6YjKNrVL62BB",
    "new_uri": "https://dup-in-isolate.s3.us-west-1.amazonaws.com/3865-lock.json"
  },
  {
    "mint_account": "4Ymx9HAAeMGtQv4sd3XwGpmaVzPzZSRDqHtZbb65pWF4",
    "new_uri": "https://dup-in-isolate.s3.us-west-1.amazonaws.com/103-lock.json"
  },
  {
    "mint_account": "5LNSqAwPyJ2bL4QQ8d83tEHfV2MbTRgNy6ZDWT8BKjmc",
    "new_uri": "https://dup-in-isolate.s3.us-west-1.amazonaws.com/3689-lock.json"
  },
  {
    "mint_account": "91GxXjXgMDV1S78X9CQ4H9wmv4WG1vvgq8dHMmy6bD6A",
    "new_uri": "https://dup-in-isolate.s3.us-west-1.amazonaws.com/3691-lock.json"
  },
  {
    "mint_account": "6MkvnHghoXgWuf3gPiXJi2JRzPoirsMGjSUsy8o8xYrd",
    "new_uri": "https://dup-in-isolate.s3.us-west-1.amazonaws.com/4122-lock.json"
  },
  {
    "mint_account": "B7iz2wTimQCEdx9yAvUmo9mQEWhTBt5ca1y8XiUNXAgP",
    "new_uri": "https://dup-in-isolate.s3.us-west-1.amazonaws.com/4166-lock.json"
  },
  {
    "mint_account": "9rxA2xHD1nmk6cVx616XerXFRcvp35JRadFAVVTG6ntf",
    "new_uri": "https://dup-in-isolate.s3.us-west-1.amazonaws.com/111-lock.json"
  },
  {
    "mint_account": "7HX7wwmEs8fyzrwannRVie9JBuczteHWkXXZyWpmStys",
    "new_uri": "https://dup-in-isolate.s3.us-west-1.amazonaws.com/72-lock.json"
  },
  {
    "mint_account": "EXe7bP2NxBtnxZckc2rQpbWpwzM7gKu6vt3RRi1wRJo",
    "new_uri": "https://dup-in-isolate.s3.us-west-1.amazonaws.com/1754-lock.json"
  },
  {
    "mint_account": "BuV3hizY78cwmvJm6H7bceLHYKgTM6on88wA6t2uVyUM",
    "new_uri": "https://dup-in-isolate.s3.us-west-1.amazonaws.com/1788-lock.json"
  },
  {
    "mint_account": "HasuKsqFMPuMoecPmq34YdtNmdHvZBF1rqJkUoZ6PJTn",
    "new_uri": "https://dup-in-isolate.s3.us-west-1.amazonaws.com/1815-lock.json"
  },
  {
    "mint_account": "2vnj6deXLFcGW7HRdigxuzM1RiMXcPzQFRK14X8XF7wF",
    "new_uri": "https://dup-in-isolate.s3.us-west-1.amazonaws.com/3533-lock.json"
  },
  {
    "mint_account": "BFnDHsJDFL7BFPdstH6y1BKrBq15M6HDZEmhYPZHXUSK",
    "new_uri": "https://dup-in-isolate.s3.us-west-1.amazonaws.com/4103-lock.json"
  },
  {
    "mint_account": "9x3cWM4gkjBGdYWahMkGE3Y54shqEDHeyMyBEtcekSoM",
    "new_uri": "https://dup-in-isolate.s3.us-west-1.amazonaws.com/3934-lock.json"
  },
  {
    "mint_account": "2Zw3tPr7hEr2jB1EtKwxcvs3KQbgh8YFS6Fid5u1MWHe",
    "new_uri": "https://dup-in-isolate.s3.us-west-1.amazonaws.com/3655-lock.json"
  },
  {
    "mint_account": "45Gj6MxPnqyT2u6a4qHcDKHT8kAmVciXBfgFfCyYN33T",
    "new_uri": "https://dup-in-isolate.s3.us-west-1.amazonaws.com/3734-lock.json"
  },
  {
    "mint_account": "BFYB7AD4bU6bn8R7sEJqybWTLBuaKSbYq898qhQtDc9Z",
    "new_uri": "https://dup-in-isolate.s3.us-west-1.amazonaws.com/134-lock.json"
  },
  {
    "mint_account": "81kp2LdoC8oDACXoVDqqiSVifd1jq23cKgghRbTdfHU7",
    "new_uri": "https://dup-in-isolate.s3.us-west-1.amazonaws.com/3585-lock.json"
  },
  {
    "mint_account": "5ZX3GjqgM6kZ9nVkSQxdkERLEHRfEPrao42VQG5FcGp3",
    "new_uri": "https://dup-in-isolate.s3.us-west-1.amazonaws.com/1813-lock.json"
  },
  {
    "mint_account": "3BPV7TRYniTJmxLRBV7WAU6ahwnEBmsXKVaY2kgV3rkY",
    "new_uri": "https://dup-in-isolate.s3.us-west-1.amazonaws.com/1786-lock.json"
  },
  {
    "mint_account": "9LJP1MsaQx1FY1zx5ywJa8gN8FZqgjN9qpnLubgj6GvR",
    "new_uri": "https://dup-in-isolate.s3.us-west-1.amazonaws.com/3675-lock.json"
  },
  {
    "mint_account": "5u9yGzYMTYqUfyan4aRfMdBx5sohZ1xMz4kARScF835b",
    "new_uri": "https://dup-in-isolate.s3.us-west-1.amazonaws.com/87-lock.json"
  },
  {
    "mint_account": "8W8bVx9BCP8Ph5c2TWG7N2D1t47TDTR3BUXrcc91Rqtq",
    "new_uri": "https://dup-in-isolate.s3.us-west-1.amazonaws.com/1782-lock.json"
  },
  {
    "mint_account": "9TQBqPePypvmc5Vf6L6mQHXdbxhnDk6Fxq4rVHQHCy7z",
    "new_uri": "https://dup-in-isolate.s3.us-west-1.amazonaws.com/1809-lock.json"
  },
  {
    "mint_account": "BrDSWg6ce2cUNm1EvDectAwQZTXtdYM57RU8rQwkvPcj",
    "new_uri": "https://dup-in-isolate.s3.us-west-1.amazonaws.com/3570-lock.json"
  },
  {
    "mint_account": "G7aKCXW7jb7M8Mhz6ZpiVAejv4d4sj6X9RfU2Rcw1s9b",
    "new_uri": "https://dup-in-isolate.s3.us-west-1.amazonaws.com/3725-lock.json"
  },
  {
    "mint_account": "4rmi9xUgyPHVYyQRVPbvp1LqiqK3aYP6sv3aVkByD8QS",
    "new_uri": "https://dup-in-isolate.s3.us-west-1.amazonaws.com/1707-lock.json"
  },
  {
    "mint_account": "Hyrs9jAubqW4BXiKV1LuEwMzBoSk2tD9iLdNAQMzkjdg",
    "new_uri": "https://dup-in-isolate.s3.us-west-1.amazonaws.com/3907-lock.json"
  },
  {
    "mint_account": "66CKgyP4u4D1CTgW3ePWdpri5gBs8mTjkN2o5q8BdtyN",
    "new_uri": "https://dup-in-isolate.s3.us-west-1.amazonaws.com/3908-lock.json"
  },
  {
    "mint_account": "A1TTMGtgt9obCS2w8R4YSuCJdybxp8iVUX1dggDufKSk",
    "new_uri": "https://dup-in-isolate.s3.us-west-1.amazonaws.com/3604-lock.json"
  },
  {
    "mint_account": "94hJbK5PboHcXNa8bwVUDirb8we3VcSyUUfom1eXd6Py",
    "new_uri": "https://dup-in-isolate.s3.us-west-1.amazonaws.com/62-lock.json"
  },
  {
    "mint_account": "EW1iFv2HCQJ3ZWdUrKSxDXaBcMQ6F2jpVbqKLjxsovgr",
    "new_uri": "https://dup-in-isolate.s3.us-west-1.amazonaws.com/3609-lock.json"
  },
  {
    "mint_account": "2PkP6ZacCrTs3J3nKYwExz1pUYXP99TtHWX73U9b6dWV",
    "new_uri": "https://dup-in-isolate.s3.us-west-1.amazonaws.com/100-lock.json"
  },
  {
    "mint_account": "J3sSBCKreQ4uHgEjjbXo1PvY4Rx3nKkZwDhbAoRusxtu",
    "new_uri": "https://dup-in-isolate.s3.us-west-1.amazonaws.com/61-lock.json"
  },
  {
    "mint_account": "9gmsHu8TjsdPoUiJyTRXnj5Nr3XSMXshhxsNDpSLAvWL",
    "new_uri": "https://dup-in-isolate.s3.us-west-1.amazonaws.com/64-lock.json"
  },
  {
    "mint_account": "A3gNpCTzTGsjhhZwtUMdEvzSzPSxDZd1jVJM1iLfTTPJ",
    "new_uri": "https://dup-in-isolate.s3.us-west-1.amazonaws.com/105-lock.json"
  },
  {
    "mint_account": "5Gfa6kiTWB5cjj8wdxLg5EAMShutMDoE9ZdwwX98UKa2",
    "new_uri": "https://dup-in-isolate.s3.us-west-1.amazonaws.com/66-lock.json"
  },
  {
    "mint_account": "DEZVhknA9oc5tQS1jY9kWRrmWRXcSiEPT7WZfJMt3Y4V",
    "new_uri": "https://dup-in-isolate.s3.us-west-1.amazonaws.com/68-lock.json"
  },
  {
    "mint_account": "19ggHPsvQBNeaoVCyqxNpWLiUErTezz8z5W67ggv392",
    "new_uri": "https://dup-in-isolate.s3.us-west-1.amazonaws.com/107-lock.json"
  },
  {
    "mint_account": "Bq2su7LnbKWReqjdSvX6keykpy4BeMvPBnA2WLT8U5pH",
    "new_uri": "https://dup-in-isolate.s3.us-west-1.amazonaws.com/69-lock.json"
  },
  {
    "mint_account": "9jBCxdeqrdPV8qhDbrkswmbAJp2LjTysioDvR9cJvt11",
    "new_uri": "https://dup-in-isolate.s3.us-west-1.amazonaws.com/110-lock.json"
  },
  {
    "mint_account": "Ad62D9oxmP61aSAorrA3z9xFPkhpd7HQADwTbTWCHXur",
    "new_uri": "https://dup-in-isolate.s3.us-west-1.amazonaws.com/3630-lock.json"
  },
  {
    "mint_account": "DeYaTWwYLPYQJfBoWinHVUobpc87J2ryoa3NLXPPRx8A",
    "new_uri": "https://dup-in-isolate.s3.us-west-1.amazonaws.com/73-lock.json"
  },
  {
    "mint_account": "BG1tfDJsWMafi96WNX4S73q7ACv7J7tGSCyLnEF7e2sJ",
    "new_uri": "https://dup-in-isolate.s3.us-west-1.amazonaws.com/114-lock.json"
  },
  {
    "mint_account": "FWmht8jD3etQqRajNeujAeYr17HvM3pMYwNGPUnWeCPg",
    "new_uri": "https://dup-in-isolate.s3.us-west-1.amazonaws.com/76-lock.json"
  },
  {
    "mint_account": "2uTZznFadzLmgoz2j8EuGAKxVjGw6ELRd7x87yv12VTg",
    "new_uri": "https://dup-in-isolate.s3.us-west-1.amazonaws.com/78-lock.json"
  },
  {
    "mint_account": "D1QEZQZAmJPHePb7XTx1WWrUKgYwU6z5hpcX5UhfjYHS",
    "new_uri": "https://dup-in-isolate.s3.us-west-1.amazonaws.com/77-lock.json"
  },
  {
    "mint_account": "7K9iDTN7761cmYEmWB4VXvdod3jTUh3BtZYcQ2uTH7qh",
    "new_uri": "https://dup-in-isolate.s3.us-west-1.amazonaws.com/119-lock.json"
  },
  {
    "mint_account": "NbZEVUoHiT2eEDHosssgQ8XAzVyRJdGfp5a2fjoPj9E",
    "new_uri": "https://dup-in-isolate.s3.us-west-1.amazonaws.com/4117-lock.json"
  },
  {
    "mint_account": "BWPwhDMb8CARvhZnhjoZ1YcwmVtJWwbXiFHerPD2rQMn",
    "new_uri": "https://dup-in-isolate.s3.us-west-1.amazonaws.com/120-lock.json"
  },
  {
    "mint_account": "4kLghzQhrktCdj7bDLinRsM28vdfup7QkREvG4oUxCNF",
    "new_uri": "https://dup-in-isolate.s3.us-west-1.amazonaws.com/121-lock.json"
  },
  {
    "mint_account": "7T31PhccJsyNRZDQ4vTLC37Fn5uWRXTm3izEvdcR8iBD",
    "new_uri": "https://dup-in-isolate.s3.us-west-1.amazonaws.com/122-lock.json"
  },
  {
    "mint_account": "7PRjihH9Ka5mQVgLFqXXJ9Fd2JpdsQpQY1iftigYFK61",
    "new_uri": "https://dup-in-isolate.s3.us-west-1.amazonaws.com/83-lock.json"
  },
  {
    "mint_account": "4ZUC3jkBUWoUNRJ5Tz571kaGMQotTAEPfJ3N3QZTcnGZ",
    "new_uri": "https://dup-in-isolate.s3.us-west-1.amazonaws.com/124-lock.json"
  },
  {
    "mint_account": "69NbMhoDgTbE58TS2PgHC9U8ezvAxwSw7aDsVB8P96aD",
    "new_uri": "https://dup-in-isolate.s3.us-west-1.amazonaws.com/125-lock.json"
  },
  {
    "mint_account": "E3iqNXkTZn6ht6ZWatRN8oCdaNewrJX7ErJLkeXm48pZ",
    "new_uri": "https://dup-in-isolate.s3.us-west-1.amazonaws.com/1694-lock.json"
  },
  {
    "mint_account": "Bv4jD1y9tZHvoTAaaHYWg3Hkrqy8jnTxsHnxoHaDjjba",
    "new_uri": "https://dup-in-isolate.s3.us-west-1.amazonaws.com/3557-lock.json"
  },
  {
    "mint_account": "7y4cZUoML1MvrZikrYdoiBpL2p7mUcVD12kw41411ggD",
    "new_uri": "https://dup-in-isolate.s3.us-west-1.amazonaws.com/3669-lock.json"
  },
  {
    "mint_account": "BuE6sCeU9mCzAsjGco5QroEPrCMbb93FkSUfU5Rn9s9r",
    "new_uri": "https://dup-in-isolate.s3.us-west-1.amazonaws.com/3581-lock.json"
  },
  {
    "mint_account": "BfT8RMSds6dBazKdPrzfxatsvCGGthFMAiuoiFruHRSN",
    "new_uri": "https://dup-in-isolate.s3.us-west-1.amazonaws.com/126-lock.json"
  },
  {
    "mint_account": "7s5Mjkycqgs1yTGFLjeVxy6US9zwFLQm4RtJBTzv46ZK",
    "new_uri": "https://dup-in-isolate.s3.us-west-1.amazonaws.com/90-lock.json"
  },
  {
    "mint_account": "BMfU194R6CSzvWXJ5ejX2EYXyDrCBsWfDajbUR49cemJ",
    "new_uri": "https://dup-in-isolate.s3.us-west-1.amazonaws.com/129-lock.json"
  },
  {
    "mint_account": "Cdat88MBuazbJKtAkxpP1UjKRh3az4jE5cqKdLrWSGK5",
    "new_uri": "https://dup-in-isolate.s3.us-west-1.amazonaws.com/132-lock.json"
  },
  {
    "mint_account": "2xGCiR6JDGMXYv4XKXuTbb1V3GFmC258Qm4CgvzL59Rg",
    "new_uri": "https://dup-in-isolate.s3.us-west-1.amazonaws.com/4040-lock.json"
  },
  {
    "mint_account": "9eyNuydTiMbdTWcSk61VWW7rq2TNKTUPNArw6ko9sCGU",
    "new_uri": "https://dup-in-isolate.s3.us-west-1.amazonaws.com/91-lock.json"
  },
  {
    "mint_account": "GGcKWzuS8Dyu7PctPBzjkU2KAqkAgdKFBxzjxF5t3UGM",
    "new_uri": "https://dup-in-isolate.s3.us-west-1.amazonaws.com/1777-lock.json"
  },
  {
    "mint_account": "88apZgC2D55AASmUdCqW3WwEbQAvXNGhsi4AqngMY5FU",
    "new_uri": "https://dup-in-isolate.s3.us-west-1.amazonaws.com/1804-lock.json"
  },
  {
    "mint_account": "2tg2SwiLCMHu8vBuS3Z3SNYzPKyx99JKQxnoSeqDn8JC",
    "new_uri": "https://dup-in-isolate.s3.us-west-1.amazonaws.com/133-lock.json"
  },
  {
    "mint_account": "2vrDA2oDpY5HJukQ9azqRVPtiKFk28yjMLeYqqTJHsyZ",
    "new_uri": "https://dup-in-isolate.s3.us-west-1.amazonaws.com/135-lock.json"
  },
  {
    "mint_account": "GvWQdmTqqZ9hy9k2jD1H3YmYS8Y7ZsxDpb5wSREqttH9",
    "new_uri": "https://dup-in-isolate.s3.us-west-1.amazonaws.com/96-lock.json"
  },
  {
    "mint_account": "8TteEqUH5uVPkYDVrt43bLetN9UkoewLQTu2o4RNdFUU",
    "new_uri": "https://dup-in-isolate.s3.us-west-1.amazonaws.com/138-lock.json"
  },
  {
    "mint_account": "BKkqocRUoXSBags1y1KWoTYD4N6L3KSEHdTgeGkniVNb",
    "new_uri": "https://dup-in-isolate.s3.us-west-1.amazonaws.com/97-lock.json"
  },
  {
    "mint_account": "BvcMEeBdgDmn2yFGkQNwm3WmjgSd2uyBV3AmTEQEYAgx",
    "new_uri": "https://dup-in-isolate.s3.us-west-1.amazonaws.com/3561-lock.json"
  },
  {
    "mint_account": "37jvi7Geko8iGdiMViekMAFXkzwpeofcV5HE6PL2GYaf",
    "new_uri": "https://dup-in-isolate.s3.us-west-1.amazonaws.com/139-lock.json"
  },
  {
    "mint_account": "GkeP1xf5tC1hu25ZPshkb8Hk2pUFR5Lf6ePLVNVqZraN",
    "new_uri": "https://dup-in-isolate.s3.us-west-1.amazonaws.com/3565-lock.json"
  },
  {
    "mint_account": "2r4QFmcS5P1KbHEXUhHf8znAf9hbzBcf2hLGz8jEZLQo",
    "new_uri": "https://dup-in-isolate.s3.us-west-1.amazonaws.com/1740-lock.json"
  },
  {
    "mint_account": "3tg2ec8gb4tTUpPwUQxFWrwGisjXB89HuW2fazLa1AEt",
    "new_uri": "https://dup-in-isolate.s3.us-west-1.amazonaws.com/3960-lock.json"
  },
  {
    "mint_account": "FvYRQAY7C4XFaGkGrNjb7Wim1iBwVMGbYoqSJBePgTXK",
    "new_uri": "https://dup-in-isolate.s3.us-west-1.amazonaws.com/3635-lock.json"
  },
  {
    "mint_account": "BSGoro8LJvA5TU7K3kPSu9xgr9gnuSK8RFbFpGpwc1wW",
    "new_uri": "https://dup-in-isolate.s3.us-west-1.amazonaws.com/4022-lock.json"
  },
  {
    "mint_account": "HkftYGYNm2BBHJiKb3auJhze6eQ49f1dHkTuYJ9LSeQb",
    "new_uri": "https://dup-in-isolate.s3.us-west-1.amazonaws.com/3670-lock.json"
  },
  {
    "mint_account": "EECH55cNT33nLctU4jhiqATMCNdZyEhvtYH2GB2JqBZA",
    "new_uri": "https://dup-in-isolate.s3.us-west-1.amazonaws.com/3593-lock.json"
  },
  {
    "mint_account": "FnoHdqxaSUrxePHP4xyLx7bRUGPQou3uwYrtFPcnwq6U",
    "new_uri": "https://dup-in-isolate.s3.us-west-1.amazonaws.com/4088-lock.json"
  },
  {
    "mint_account": "7DMyGVNhj2CBW4zocFvNkbZP2f1cMN1n2uXPeAckTkWR",
    "new_uri": "https://dup-in-isolate.s3.us-west-1.amazonaws.com/3613-lock.json"
  },
  {
    "mint_account": "FfYGjMg5562XJm6Ev2JLAk73Jba2q97xeUfbR5E2sfyL",
    "new_uri": "https://dup-in-isolate.s3.us-west-1.amazonaws.com/4000-lock.json"
  },
  {
    "mint_account": "DRN2HpWh7XgLcivjjD86MCYZyNY5TJGnKYX1Yo86J9XS",
    "new_uri": "https://dup-in-isolate.s3.us-west-1.amazonaws.com/1774-lock.json"
  },
  {
    "mint_account": "A9brgrAgXYjaXoS5chF2LQqdF5F3iAhboxBMmvcpUuFm",
    "new_uri": "https://dup-in-isolate.s3.us-west-1.amazonaws.com/1721-lock.json"
  },
  {
    "mint_account": "6RdH2rgd85feixKvTGVhRfkbMmpaYHgCp7MPmsLPr9cy",
    "new_uri": "https://dup-in-isolate.s3.us-west-1.amazonaws.com/3648-lock.json"
  },
  {
    "mint_account": "2ub1Rhkddxo4hDAsAtL9abRWKrUYmLq7dPNrLKKQmum5",
    "new_uri": "https://dup-in-isolate.s3.us-west-1.amazonaws.com/4051-lock.json"
  },
  {
    "mint_account": "9VnFUFpaucqoECNQsa5F3rxkzYKzQJxXusvVVcAESvrB",
    "new_uri": "https://dup-in-isolate.s3.us-west-1.amazonaws.com/3519-lock.json"
  },
  {
    "mint_account": "5miWuSUKiXxa31ggwpjNcTfGduZcPnwNxGnfGAtUajKJ",
    "new_uri": "https://dup-in-isolate.s3.us-west-1.amazonaws.com/3686-lock.json"
  },
  {
    "mint_account": "57yAGoPugwRgJQ5A7qiFPFjBrSR2EJUAavJTSmVt6zXz",
    "new_uri": "https://dup-in-isolate.s3.us-west-1.amazonaws.com/3661-lock.json"
  },
  {
    "mint_account": "BnSK9idWAoPB2tu4ADLgXWHz7vo8EGQcmFG2WF9nrzpJ",
    "new_uri": "https://dup-in-isolate.s3.us-west-1.amazonaws.com/3582-lock.json"
  },
  {
    "mint_account": "3iZQomNMW7McUHxg3C9NWTauPac2fYU17xXJm3RhGKmk",
    "new_uri": "https://dup-in-isolate.s3.us-west-1.amazonaws.com/88-lock.json"
  },
  {
    "mint_account": "GWYrjhzEhHAb6d3oJDL8kMZmH2XuTUfhVK1eU8KqoT87",
    "new_uri": "https://dup-in-isolate.s3.us-west-1.amazonaws.com/1697-lock.json"
  },
  {
    "mint_account": "FPAaso35uTrvSgLMAwTohM9i7svVhK7GsjEGcM9meMPX",
    "new_uri": "https://dup-in-isolate.s3.us-west-1.amazonaws.com/3618-lock.json"
  },
  {
    "mint_account": "2gjvXdsPrBSxy2f8CgWMcE7XNvvbVGUtyGmbsMC99SKx",
    "new_uri": "https://dup-in-isolate.s3.us-west-1.amazonaws.com/4038-lock.json"
  },
  {
    "mint_account": "HAP5pBVSJLdExwNX4kZjKfx4YEAyekDNAa335KpxmXit",
    "new_uri": "https://dup-in-isolate.s3.us-west-1.amazonaws.com/4246-lock.json"
  },
  {
    "mint_account": "H3qgKV8DVaWrCmdtXB9BgDfs4FrLB7EpdDHE9Eyvh7aP",
    "new_uri": "https://dup-in-isolate.s3.us-west-1.amazonaws.com/3616-lock.json"
  },
  {
    "mint_account": "KVWi5MsHF7DM2wfzD3Uhy2rZiiBuRhtCtXf6geDjXjV",
    "new_uri": "https://dup-in-isolate.s3.us-west-1.amazonaws.com/3887-lock.json"
  },
  {
    "mint_account": "3EE6x2Xrpixti9qMx6MJCQ8g8ZTrSEBqdfiXwCs8T68r",
    "new_uri": "https://dup-in-isolate.s3.us-west-1.amazonaws.com/3651-lock.json"
  },
  {
    "mint_account": "FR5eXquGmjBKfahuA7yYFpD6CYqzJS55W2eSr2Zj7e6Z",
    "new_uri": "https://dup-in-isolate.s3.us-west-1.amazonaws.com/3681-lock.json"
  },
  {
    "mint_account": "8wbnj394ZvLL3BaqBWsKW6mrS3eNWtaG7BY7yNMnzxKG",
    "new_uri": "https://dup-in-isolate.s3.us-west-1.amazonaws.com/3736-lock.json"
  },
  {
    "mint_account": "2JgmcHCx32NcVqFdDvVqX9aZAVt5bvkNFy7xJCnd9J9H",
    "new_uri": "https://dup-in-isolate.s3.us-west-1.amazonaws.com/3579-lock.json"
  },
  {
    "mint_account": "78DgNcLX9qZnpaSKncDCfwMZxXWm4tvT4KxXwf46JJ1Z",
    "new_uri": "https://dup-in-isolate.s3.us-west-1.amazonaws.com/3583-lock.json"
  },
  {
    "mint_account": "61oW2sdCqCXfip3knaSsD3Tz76EgozAvRQqrPrRmAp6j",
    "new_uri": "https://dup-in-isolate.s3.us-west-1.amazonaws.com/3637-lock.json"
  },
  {
    "mint_account": "9rJPaASYhV8h3HgDhoTPYwqvLpG67fuRoNU38cw7kUVU",
    "new_uri": "https://dup-in-isolate.s3.us-west-1.amazonaws.com/3941-lock.json"
  },
  {
    "mint_account": "CB2UsiQVocNXuTzryGYiL2LEWhDnoteFWEzSJu42NuHt",
    "new_uri": "https://dup-in-isolate.s3.us-west-1.amazonaws.com/3571-lock.json"
  },
  {
    "mint_account": "3Riu5DMJ1L8VKJY9SzC2MJPB8KBduesDvvS6scm2ntWx",
    "new_uri": "https://dup-in-isolate.s3.us-west-1.amazonaws.com/3808-lock.json"
  },
  {
    "mint_account": "4D3YiUUhzetUEaP4BwzPgBrZHE2NrpjFHZdrJ5DL9Zz6",
    "new_uri": "https://dup-in-isolate.s3.us-west-1.amazonaws.com/3643-lock.json"
  },
  {
    "mint_account": "3JcSAfXBMHG5CvPJMn1wPCknFu2voQZm12MpB4nYjxP5",
    "new_uri": "https://dup-in-isolate.s3.us-west-1.amazonaws.com/4031-lock.json"
  },
  {
    "mint_account": "Fz9A2ZzGhmj5seoAZfyH88jjKioVRjCnMSHiPWHNd6AV",
    "new_uri": "https://dup-in-isolate.s3.us-west-1.amazonaws.com/4099-lock.json"
  },
  {
    "mint_account": "5TiDPntT4CMb1BvwzojnRB3jT19TTALnhZuixMdu5KG7",
    "new_uri": "https://dup-in-isolate.s3.us-west-1.amazonaws.com/1766-lock.json"
  },
  {
    "mint_account": "HnLT5L2aGwnm9BaWAWdQzK86K7ATCFFmni5LhG4mkFLg",
    "new_uri": "https://dup-in-isolate.s3.us-west-1.amazonaws.com/1713-lock.json"
  },
  {
    "mint_account": "53GpSVNmjak2yvYn1aCQ9RoiCUDfBZxZTxkVV9bvPeVa",
    "new_uri": "https://dup-in-isolate.s3.us-west-1.amazonaws.com/3806-lock.json"
  },
  {
    "mint_account": "AKkq1QHK1rvRD1sEkd1fVi572eVBUu9nk7U5QCSNMhiD",
    "new_uri": "https://dup-in-isolate.s3.us-west-1.amazonaws.com/4228-lock.json"
  },
  {
    "mint_account": "5scvoY9ZznH7dFAat25iBSfRGC5zKbYqLdUMZwrD7Db4",
    "new_uri": "https://dup-in-isolate.s3.us-west-1.amazonaws.com/4234-lock.json"
  },
  {
    "mint_account": "EJod9RHXEaUWgh4bYmqBWjFRexac4NpjgVbf9oHvbzfZ",
    "new_uri": "https://dup-in-isolate.s3.us-west-1.amazonaws.com/3898-lock.json"
  },
  {
    "mint_account": "EqUoE1t1CYEUnTwRW82dsZkAY7e3uGfaDyNQEzosjPvp",
    "new_uri": "https://dup-in-isolate.s3.us-west-1.amazonaws.com/3642-lock.json"
  },
  {
    "mint_account": "CD6BWtSWhUGJuG2xhnL5AXzSqirsb5ZCUfnhtfoFUgBj",
    "new_uri": "https://dup-in-isolate.s3.us-west-1.amazonaws.com/3818-lock.json"
  },
  {
    "mint_account": "HHrbfrcqD3H2yC17zD5nB8ETR9baHeeFwmqD7pACSjBz",
    "new_uri": "https://dup-in-isolate.s3.us-west-1.amazonaws.com/4078-lock.json"
  },
  {
    "mint_account": "2GxeV5nopbVYRKiasG6sWW6XDNryK9t9SRW2RZaX3oiX",
    "new_uri": "https://dup-in-isolate.s3.us-west-1.amazonaws.com/3723-lock.json"
  },
  {
    "mint_account": "Ey6TK3cav3BaDG8oMCHgvCJhbaALDAK1Pa2sVQ8QZMng",
    "new_uri": "https://dup-in-isolate.s3.us-west-1.amazonaws.com/3760-lock.json"
  },
  {
    "mint_account": "Akm6C4YG73WfmWsByV8GVM38KatutFH5xMz41xLX8UNE",
    "new_uri": "https://dup-in-isolate.s3.us-west-1.amazonaws.com/3764-lock.json"
  },
  {
    "mint_account": "5ZA1DwRYXex1r7hB9uzmLLu1tWXikKbpQbj8bEqUM7cQ",
    "new_uri": "https://dup-in-isolate.s3.us-west-1.amazonaws.com/3742-lock.json"
  },
  {
    "mint_account": "EVm2CBC369QKYudEYHBxsv1EEvcRnHLCk2gJ58Y9PQjg",
    "new_uri": "https://dup-in-isolate.s3.us-west-1.amazonaws.com/3746-lock.json"
  },
  {
    "mint_account": "6bZSDtyXLzqZvbDNWz2FvHhw5ZsmfQYYeog8pUSZpuK6",
    "new_uri": "https://dup-in-isolate.s3.us-west-1.amazonaws.com/4113-lock.json"
  },
  {
    "mint_account": "5K5XcVmXazZ215fezZuahuke2jR3dtNQJ7ojXXvWS2Mz",
    "new_uri": "https://dup-in-isolate.s3.us-west-1.amazonaws.com/4116-lock.json"
  },
  {
    "mint_account": "CxwLAvvVj9FPt2KvoDzjKMbiVLYf63jTHfNFmtoFRzmm",
    "new_uri": "https://dup-in-isolate.s3.us-west-1.amazonaws.com/3755-lock.json"
  },
  {
    "mint_account": "GdmUPP83TL5ziPfbjDfByEmj4qeBoT5C4798qKtGPrYV",
    "new_uri": "https://dup-in-isolate.s3.us-west-1.amazonaws.com/4120-lock.json"
  },
  {
    "mint_account": "DThAsiZgytmY7Do1bLgTk1jHRKtHifAx5DE8TnwGUB9m",
    "new_uri": "https://dup-in-isolate.s3.us-west-1.amazonaws.com/4123-lock.json"
  },
  {
    "mint_account": "GyDerbSZ9wHG39Y4x4pbtCoaSMvpymWoVm3tJuVUYeyH",
    "new_uri": "https://dup-in-isolate.s3.us-west-1.amazonaws.com/4125-lock.json"
  },
  {
    "mint_account": "BZcsFhTgPStesHgncpSs7ibNs1sa6w4hzd38gTnVbSp3",
    "new_uri": "https://dup-in-isolate.s3.us-west-1.amazonaws.com/3770-lock.json"
  },
  {
    "mint_account": "CrCHCEmsQTtQZtsqhpj7n86eA6MreTVSrBtzvQSVFP36",
    "new_uri": "https://dup-in-isolate.s3.us-west-1.amazonaws.com/3771-lock.json"
  },
  {
    "mint_account": "FheyMdcqkfUkJmBTu8PsfLvPvWqXya9JNUGF9dcPFh8w",
    "new_uri": "https://dup-in-isolate.s3.us-west-1.amazonaws.com/4140-lock.json"
  },
  {
    "mint_account": "FGUd32JwNqWGU8kNtyjPaFEEXotpyk8MAUNjWjRAuJCd",
    "new_uri": "https://dup-in-isolate.s3.us-west-1.amazonaws.com/4142-lock.json"
  },
  {
    "mint_account": "kdZWYwT3QCXriNxjagG3gpAnphiKNTzVshwK1a7uGUH",
    "new_uri": "https://dup-in-isolate.s3.us-west-1.amazonaws.com/4149-lock.json"
  },
  {
    "mint_account": "9vdkkS3eqkRGQsTRNCDhay5sN36wwJreDF51JxGaTrbB",
    "new_uri": "https://dup-in-isolate.s3.us-west-1.amazonaws.com/4155-lock.json"
  },
  {
    "mint_account": "ArYoBfN5TmhQsouZbxMf6Dt5wAfd8SQy8YT6PPuRKLDq",
    "new_uri": "https://dup-in-isolate.s3.us-west-1.amazonaws.com/4152-lock.json"
  },
  {
    "mint_account": "AbHpJKiPfXhvHDKZJQj9MpQibZK5zNr2kpE26SykmPjn",
    "new_uri": "https://dup-in-isolate.s3.us-west-1.amazonaws.com/3795-lock.json"
  },
  {
    "mint_account": "DwH6XZ6fUEahVqDJDBGXTSGHFYRnTCmQu5oKWbanVj6N",
    "new_uri": "https://dup-in-isolate.s3.us-west-1.amazonaws.com/4163-lock.json"
  },
  {
    "mint_account": "4NydStgHMn2GmStS7GoXGpWTXArKnUfbLivyNyNsdzFH",
    "new_uri": "https://dup-in-isolate.s3.us-west-1.amazonaws.com/3801-lock.json"
  },
  {
    "mint_account": "BFgL68nrmthYM9XKnhNhqMsfoeMh65JepR8JeDQywLT6",
    "new_uri": "https://dup-in-isolate.s3.us-west-1.amazonaws.com/3803-lock.json"
  },
  {
    "mint_account": "8WEMYe8sokTgvzzT6zwRivspPnuAJKp6mvQSPaY6dxAf",
    "new_uri": "https://dup-in-isolate.s3.us-west-1.amazonaws.com/3804-lock.json"
  },
  {
    "mint_account": "7W5zwQH65r9SC56vb3qBqNpdCe3hBxeHriNYgpURFLkQ",
    "new_uri": "https://dup-in-isolate.s3.us-west-1.amazonaws.com/3810-lock.json"
  },
  {
    "mint_account": "thxmW2TdBuDU3L9i7Q8cceFvHY5wQEWdREHGZbo7wnz",
    "new_uri": "https://dup-in-isolate.s3.us-west-1.amazonaws.com/3814-lock.json"
  },
  {
    "mint_account": "7Yx49uHp4GKVSa8sNKZkqW9asNbexHsgB7ffmrY6hcib",
    "new_uri": "https://dup-in-isolate.s3.us-west-1.amazonaws.com/3812-lock.json"
  },
  {
    "mint_account": "FbSxCQ1fFhzHjdBs7rRppudQYhmjCFBxH4GMh7hHAZju",
    "new_uri": "https://dup-in-isolate.s3.us-west-1.amazonaws.com/3817-lock.json"
  },
  {
    "mint_account": "CBTvQHFRmEbCcU62GktvmX8BbmTNJJmdsa5nNGaJRAou",
    "new_uri": "https://dup-in-isolate.s3.us-west-1.amazonaws.com/3816-lock.json"
  },
  {
    "mint_account": "3MuJviPD2ngZ7WmAGxw48FhU5PnTaQyfCWm4HVm5hgb4",
    "new_uri": "https://dup-in-isolate.s3.us-west-1.amazonaws.com/3834-lock.json"
  },
  {
    "mint_account": "ERqYrMZ2b7uX3q2ey1AXXHKzG2ur8cd91KzJ1nzCyEeJ",
    "new_uri": "https://dup-in-isolate.s3.us-west-1.amazonaws.com/3836-lock.json"
  },
  {
    "mint_account": "A3Pwc16MTH5gr4i9XbCy4Q7AqTMAFV6UJVPRmYRJUxES",
    "new_uri": "https://dup-in-isolate.s3.us-west-1.amazonaws.com/4203-lock.json"
  },
  {
    "mint_account": "DMcXsdS5GSeo7GFBo4r8iskLUX5Ah6r6bgMxFgfbMqyL",
    "new_uri": "https://dup-in-isolate.s3.us-west-1.amazonaws.com/3840-lock.json"
  },
  {
    "mint_account": "8pHs6a5Xz2Uv5WHa8JceJpZv8Ma3vS3fYpTVJrWQpgRM",
    "new_uri": "https://dup-in-isolate.s3.us-west-1.amazonaws.com/4209-lock.json"
  },
  {
    "mint_account": "Jc1N6FtufUjuJz63jSFD3Hnqj65jYmPzZQecuMFoeHT",
    "new_uri": "https://dup-in-isolate.s3.us-west-1.amazonaws.com/4213-lock.json"
  },
  {
    "mint_account": "4CDghSjsnoT7K1JjgZfykjrQ7YLQuEdaUn1ZMbRwqfQ4",
    "new_uri": "https://dup-in-isolate.s3.us-west-1.amazonaws.com/4214-lock.json"
  },
  {
    "mint_account": "CwN7WCUStqiVFut95sNGHttBWUSrNF8Xw8ZsCt9QQaf9",
    "new_uri": "https://dup-in-isolate.s3.us-west-1.amazonaws.com/3851-lock.json"
  },
  {
    "mint_account": "2NV3esmna49484Ft7jxzmFdFKZoh6Q4Lb2hL5nz1Mypz",
    "new_uri": "https://dup-in-isolate.s3.us-west-1.amazonaws.com/3852-lock.json"
  },
  {
    "mint_account": "5ryydgwD9bgJVAFswZmp2ESc23qJp7n5jiEj13dzXiaf",
    "new_uri": "https://dup-in-isolate.s3.us-west-1.amazonaws.com/3856-lock.json"
  },
  {
    "mint_account": "A4iNTwrwEp4VHCKZ2xvnfVRMvLHKxNZR3NpyHvWxvkf4",
    "new_uri": "https://dup-in-isolate.s3.us-west-1.amazonaws.com/4221-lock.json"
  },
  {
    "mint_account": "7m1q3iVLkCspWSBa1hZuZBLZqCLAYBC75MXtXEZHGShJ",
    "new_uri": "https://dup-in-isolate.s3.us-west-1.amazonaws.com/4229-lock.json"
  },
  {
    "mint_account": "2jUmtejCPSN7HKmaf9VdHrzMsAHok26iZz4tXiQKzu1p",
    "new_uri": "https://dup-in-isolate.s3.us-west-1.amazonaws.com/4226-lock.json"
  },
  {
    "mint_account": "4sX4z7A19aEfHvYqzVx4nfULFu5KWfmSpVrD1cZ7NwUd",
    "new_uri": "https://dup-in-isolate.s3.us-west-1.amazonaws.com/3864-lock.json"
  },
  {
    "mint_account": "6ofWc8r14jWdbuVZ3Y4S4gx2qf3AcjvX5SFHsiJjSKgJ",
    "new_uri": "https://dup-in-isolate.s3.us-west-1.amazonaws.com/4232-lock.json"
  },
  {
    "mint_account": "yVVU3LKR4metBcTU7fQ2XAa7wn5QaRQT8qpxijFUdH7",
    "new_uri": "https://dup-in-isolate.s3.us-west-1.amazonaws.com/3875-lock.json"
  },
  {
    "mint_account": "DXjvk9GdYwMR5hr4xCFAovYYzBS2QZYJBS11zCP82oh5",
    "new_uri": "https://dup-in-isolate.s3.us-west-1.amazonaws.com/4244-lock.json"
  },
  {
    "mint_account": "6cPp1DDdAzsoxy7VqM6Y2MXDm9xMpxqW4hBQavZq5DVb",
    "new_uri": "https://dup-in-isolate.s3.us-west-1.amazonaws.com/3879-lock.json"
  },
  {
    "mint_account": "aQsq2TuRpLFfidckLJiRGxrTT5HNGkM6h9WfPSBVu3N",
    "new_uri": "https://dup-in-isolate.s3.us-west-1.amazonaws.com/1787-lock.json"
  },
  {
    "mint_account": "E8V5bEvopnjoHmcimiAuqgFCyUWx1MooPJv8TfCLY2Ca",
    "new_uri": "https://dup-in-isolate.s3.us-west-1.amazonaws.com/1814-lock.json"
  },
  {
    "mint_account": "H1EZcg9SHQquoytvMYBvoP6SaYeq7Sn4rt7eDqQuhvby",
    "new_uri": "https://dup-in-isolate.s3.us-west-1.amazonaws.com/1751-lock.json"
  },
  {
    "mint_account": "FpbfjC8qHGWAQujcsg1aQJ4nSD33ZCVbjVNgiY8JTqMJ",
    "new_uri": "https://dup-in-isolate.s3.us-west-1.amazonaws.com/3658-lock.json"
  },
  {
    "mint_account": "3xq8ALb2sWTS3MYAgrgJx1yQn3N4rj2vLUqo2PFWiwD1",
    "new_uri": "https://dup-in-isolate.s3.us-west-1.amazonaws.com/1716-lock.json"
  },
  {
    "mint_account": "2iWtpLbTeiQZmwqXSsnQP3z21h7byimpG7uDpQNgM4Jo",
    "new_uri": "https://dup-in-isolate.s3.us-west-1.amazonaws.com/1769-lock.json"
  },
  {
    "mint_account": "7MyZG1pje7n5556brfr5PbQZvak5oALGY4L6ZNrYPnf8",
    "new_uri": "https://dup-in-isolate.s3.us-west-1.amazonaws.com/3660-lock.json"
  },
  {
    "mint_account": "5gq84sbPstrqj8KMoMcDtmGptC1DsajvUhCNEi1QjXdP",
    "new_uri": "https://dup-in-isolate.s3.us-west-1.amazonaws.com/3985-lock.json"
  },
  {
    "mint_account": "3qrqrqput5HM4WtMfp8p8VvGBL5SWkEvTRz1tEYdKW22",
    "new_uri": "https://dup-in-isolate.s3.us-west-1.amazonaws.com/3849-lock.json"
  },
  {
    "mint_account": "DzVoCTyE9bDsiTP9J9NTZZv2kxZgPUw6T5a41rrByE1M",
    "new_uri": "https://dup-in-isolate.s3.us-west-1.amazonaws.com/4220-lock.json"
  },
  {
    "mint_account": "4GFHu5ih55x3oD2jZ3nXSUKevQmuMHVzsZqfvjNQcTAS",
    "new_uri": "https://dup-in-isolate.s3.us-west-1.amazonaws.com/1749-lock.json"
  },
  {
    "mint_account": "GazLrtshSKNRkpH5no8t67gQCofoKyRYiX1UNpR39mB7",
    "new_uri": "https://dup-in-isolate.s3.us-west-1.amazonaws.com/4082-lock.json"
  },
  {
    "mint_account": "217NF62ywDGGwvBCQQD4b4WQ8rfhbw2U1N2SoE6JEUEY",
    "new_uri": "https://dup-in-isolate.s3.us-west-1.amazonaws.com/3981-lock.json"
  },
  {
    "mint_account": "5WDwy5ibKKmGgt81mzdf7zTUAV4mAgBBwGuQ46Jn6ic4",
    "new_uri": "https://dup-in-isolate.s3.us-west-1.amazonaws.com/3706-lock.json"
  },
  {
    "mint_account": "Ai5PJvZqibxssA8CR2Z88pyShWcHFEjn5WrfDShYLQNM",
    "new_uri": "https://dup-in-isolate.s3.us-west-1.amazonaws.com/3973-lock.json"
  },
  {
    "mint_account": "FMvYQUaQtn9BrPypdJ2MKLE4vt94LhszE37UFn389tRb",
    "new_uri": "https://dup-in-isolate.s3.us-west-1.amazonaws.com/4071-lock.json"
  },
  {
    "mint_account": "75Vi2urSgySN8FNzaE3QZg94guXVbwggguzm9HG5KtBV",
    "new_uri": "https://dup-in-isolate.s3.us-west-1.amazonaws.com/3940-lock.json"
  },
  {
    "mint_account": "J4bqML4oDsrYFhJUuZHFNozubqKxvphsSeRrycw3eF9s",
    "new_uri": "https://dup-in-isolate.s3.us-west-1.amazonaws.com/4011-lock.json"
  },
  {
    "mint_account": "DYULQWDWY3J7LLT54Pf9Wv4g7gceV6RLBH2SZrqrKvLs",
    "new_uri": "https://dup-in-isolate.s3.us-west-1.amazonaws.com/1711-lock.json"
  },
  {
    "mint_account": "8Ekv8zcbGzuKnQouBAXEVgJPcYcemcG3GhToU6zYuKJk",
    "new_uri": "https://dup-in-isolate.s3.us-west-1.amazonaws.com/4073-lock.json"
  },
  {
    "mint_account": "53VB5iFpf87iFoHf3qbskWJW5yZUUiMTt9Zs7BZR2VhF",
    "new_uri": "https://dup-in-isolate.s3.us-west-1.amazonaws.com/3924-lock.json"
  },
  {
    "mint_account": "GfYnxy75FMPvsX7tjKRb1u5xJrHufnTsMLk7kwpyYg6w",
    "new_uri": "https://dup-in-isolate.s3.us-west-1.amazonaws.com/3999-lock.json"
  },
  {
    "mint_account": "2BGx24RWW7ad7Wvp7h22fCfsBpGVzY4AzWZzyy7aW2CA",
    "new_uri": "https://dup-in-isolate.s3.us-west-1.amazonaws.com/3693-lock.json"
  },
  {
    "mint_account": "G9GnfKEFfC5MPVsZdueuJTpSJNUtNJpnE22nVvcB6kVT",
    "new_uri": "https://dup-in-isolate.s3.us-west-1.amazonaws.com/4067-lock.json"
  },
  {
    "mint_account": "H8k1j7XoqdfSrABYriUfNmzkKJQ53r1fpBFDr6kMyyVc",
    "new_uri": "https://dup-in-isolate.s3.us-west-1.amazonaws.com/1746-lock.json"
  },
  {
    "mint_account": "6dYmkTGs1JjyW6PJ3mp7VxT7YT45tAnxbMNv1hxmCnrD",
    "new_uri": "https://dup-in-isolate.s3.us-west-1.amazonaws.com/1635-lock.json"
  },
  {
    "mint_account": "CTDMWu69swTrzUszpKkZfRPViKny5Ace9UWi6ePSjba3",
    "new_uri": "https://dup-in-isolate.s3.us-west-1.amazonaws.com/1755-lock.json"
  },
  {
    "mint_account": "6h1tNHhffStFPCByk9fUoCZ7zSM2RvoTeUZbG931eYb9",
    "new_uri": "https://dup-in-isolate.s3.us-west-1.amazonaws.com/3976-lock.json"
  },
  {
    "mint_account": "MSVAQgUtLR1TQkTqhBDWasKUz15CXRsYxfzpgCtvyKG",
    "new_uri": "https://dup-in-isolate.s3.us-west-1.amazonaws.com/1744-lock.json"
  },
  {
    "mint_account": "ELKwrEuhWTxYwda9938MzwbbR37FQGAhitn4rs1oAn2A",
    "new_uri": "https://dup-in-isolate.s3.us-west-1.amazonaws.com/3780-lock.json"
  },
  {
    "mint_account": "HasdZqTLQTw5HJVhFUM3NtDLEBM63Zuswgqb3PuYkHRm",
    "new_uri": "https://dup-in-isolate.s3.us-west-1.amazonaws.com/3697-lock.json"
  },
  {
    "mint_account": "FWxKvGkCvkCSUt2dxQLzuqe3jA9jvCy4agTwAxwv8UHG",
    "new_uri": "https://dup-in-isolate.s3.us-west-1.amazonaws.com/3824-lock.json"
  },
  {
    "mint_account": "5inTT9CQvqnDVWaq1aYxaKpo6sPE7vSBDbc1RH3UxG7v",
    "new_uri": "https://dup-in-isolate.s3.us-west-1.amazonaws.com/4236-lock.json"
  },
  {
    "mint_account": "GJ2qwPfU2zNNrSpsd5mEaARiiD1FpuDirtY27g6Maa8i",
    "new_uri": "https://dup-in-isolate.s3.us-west-1.amazonaws.com/4020-lock.json"
  },
  {
    "mint_account": "8NZ26KCj18NySSSPdANx8U9bNieQ7BDYA9tgwKgea9Nu",
    "new_uri": "https://dup-in-isolate.s3.us-west-1.amazonaws.com/4151-lock.json"
  },
  {
    "mint_account": "F3hnCkJFzSriswoFbQpdEpeB9EL2v25uMEjsXakkfy9Q",
    "new_uri": "https://dup-in-isolate.s3.us-west-1.amazonaws.com/3787-lock.json"
  },
  {
    "mint_account": "iFjAFbVfDJqEF9jpDQVyxdeABDSNWwaFUdxUNf8jJ8Y",
    "new_uri": "https://dup-in-isolate.s3.us-west-1.amazonaws.com/1700-lock.json"
  },
  {
    "mint_account": "H9REGsyZcubbTzqmASvgmuVTu1gaCh4NMH241eyrk38u",
    "new_uri": "https://dup-in-isolate.s3.us-west-1.amazonaws.com/3768-lock.json"
  },
  {
    "mint_account": "J1yffMJcftMX6y3jyRzBqSPb2B41Z141k5G8RmucJGwB",
    "new_uri": "https://dup-in-isolate.s3.us-west-1.amazonaws.com/4159-lock.json"
  },
  {
    "mint_account": "5jpo2idoLfrjTAsZpUXu1pDgHgUF7Ev5ippzrFMMcr2H",
    "new_uri": "https://dup-in-isolate.s3.us-west-1.amazonaws.com/4205-lock.json"
  },
  {
    "mint_account": "CQmUXTFS7pUvz7UNEFt5XfQX5Dude2G36n4hvDSLvBdj",
    "new_uri": "https://dup-in-isolate.s3.us-west-1.amazonaws.com/3539-lock.json"
  },
  {
    "mint_account": "96jWxdDkSF7LLiYgKfXZhbZmQUaRKxizAZFu7RNQK5ZV",
    "new_uri": "https://dup-in-isolate.s3.us-west-1.amazonaws.com/3537-lock.json"
  },
  {
    "mint_account": "4n328QXEuEgASWKfgB9rdv6RiSJBuUT9KrizARsBpj2n",
    "new_uri": "https://dup-in-isolate.s3.us-west-1.amazonaws.com/3704-lock.json"
  },
  {
    "mint_account": "HbffuJPcoaY5sFFioFKD6mGptFMWWpJJaHNDR17R1qE1",
    "new_uri": "https://dup-in-isolate.s3.us-west-1.amazonaws.com/3942-lock.json"
  },
  {
    "mint_account": "EfXeeUWstGXcaGqKKiSrreg1faM2SAwMveoN4RnhwJyV",
    "new_uri": "https://dup-in-isolate.s3.us-west-1.amazonaws.com/1775-lock.json"
  },
  {
    "mint_account": "5XobU8z5K4FrxtED4Y6YpXErx653Cy2zedtWEEFRxsts",
    "new_uri": "https://dup-in-isolate.s3.us-west-1.amazonaws.com/1722-lock.json"
  },
  {
    "mint_account": "5UiwndYKtpvEsp2btxANEVQ4Ujjpo7Qx9j93abibWAfk",
    "new_uri": "https://dup-in-isolate.s3.us-west-1.amazonaws.com/3659-lock.json"
  },
  {
    "mint_account": "6iYUVuvyDJGaiCFLRRsxUvdSmAZhLkM4zmLUKStqsRa",
    "new_uri": "https://dup-in-isolate.s3.us-west-1.amazonaws.com/3638-lock.json"
  },
  {
    "mint_account": "4oBP9y6XF7WvSh1BSjyuATXdSGudjpzFDJWgBN3FoHdu",
    "new_uri": "https://dup-in-isolate.s3.us-west-1.amazonaws.com/3807-lock.json"
  },
  {
    "mint_account": "8jsKg5c5qUYAQS2wPSwRJVs9Dqf7uqwW8D8mFk3Fubj",
    "new_uri": "https://dup-in-isolate.s3.us-west-1.amazonaws.com/1695-lock.json"
  },
  {
    "mint_account": "DTDfzvuisMyxNcp6d5Z1szVGEQx7HcNcDoZd4AWGUkD2",
    "new_uri": "https://dup-in-isolate.s3.us-west-1.amazonaws.com/3732-lock.json"
  },
  {
    "mint_account": "9XFn3GPJMiSRbwngpUQcz1Gu8ogxLtbUT2Xqkk1FkHU6",
    "new_uri": "https://dup-in-isolate.s3.us-west-1.amazonaws.com/3687-lock.json"
  },
  {
    "mint_account": "6uSp6X13Xz2JbjWE4rSkyj2BYzN3m6P6WRqJ2kTDtugc",
    "new_uri": "https://dup-in-isolate.s3.us-west-1.amazonaws.com/3821-lock.json"
  },
  {
    "mint_account": "FBPzzHEviFR6FWP2Xs3URkt5U7AgYvqikYaJEVqz987K",
    "new_uri": "https://dup-in-isolate.s3.us-west-1.amazonaws.com/4032-lock.json"
  },
  {
    "mint_account": "8HhENAkjSfUQWoXpgEwfPHbrX3nmSFHKHzvP4yR1cV3o",
    "new_uri": "https://dup-in-isolate.s3.us-west-1.amazonaws.com/3993-lock.json"
  },
  {
    "mint_account": "G1rd6YDQpQTMNY6aEyyRFTnx9SoxJe3QLBr5mtoiH6u3",
    "new_uri": "https://dup-in-isolate.s3.us-west-1.amazonaws.com/3631-lock.json"
  },
  {
    "mint_account": "9SahrWES6ARcMYAk6VVJm47QNfAGWiJ5kdsJhCdx3i4M",
    "new_uri": "https://dup-in-isolate.s3.us-west-1.amazonaws.com/1692-lock.json"
  },
  {
    "mint_account": "Hd9R7SQdYFJoiiDW5pkTUSXY7vUFTioZ4mUAWoyLePY1",
    "new_uri": "https://dup-in-isolate.s3.us-west-1.amazonaws.com/3892-lock.json"
  },
  {
    "mint_account": "FN1fNmDMi1tzYjvnPkVGy2k1Rss5qkNEhJ9RuBmVe8Dm",
    "new_uri": "https://dup-in-isolate.s3.us-west-1.amazonaws.com/3820-lock.json"
  },
  {
    "mint_account": "28Maj1DrcrFgt9C4JzYaXMJChYnHnA9Bym7yYLLMkYqM",
    "new_uri": "https://dup-in-isolate.s3.us-west-1.amazonaws.com/3963-lock.json"
  },
  {
    "mint_account": "FC3fPPYkG4bEMmWHnLgRsV62X5kSE4FMdd3kkktxYUe",
    "new_uri": "https://dup-in-isolate.s3.us-west-1.amazonaws.com/3799-lock.json"
  },
  {
    "mint_account": "6M9vjVMEKQBtZSsJ1UQwRcHczxCE7fEkGwoXay9QEVR",
    "new_uri": "https://dup-in-isolate.s3.us-west-1.amazonaws.com/3990-lock.json"
  },
  {
    "mint_account": "GLXz33XoqcmSnuthG2a7T5FHEo4f7krN6BTBQeGB6xgX",
    "new_uri": "https://dup-in-isolate.s3.us-west-1.amazonaws.com/4192-lock.json"
  },
  {
    "mint_account": "365KQfpDxcxHvzF7cuvC3BfhAQxnRBTai4uTy1QBRBzs",
    "new_uri": "https://dup-in-isolate.s3.us-west-1.amazonaws.com/1634-lock.json"
  },
  {
    "mint_account": "Ajuo53eL6YiyYVLuzfVk3Y9B7jWaDnJELSVRAFTbUpBy",
    "new_uri": "https://dup-in-isolate.s3.us-west-1.amazonaws.com/1239-lock.json"
  },
  {
    "mint_account": "AYZikftFdiB2rszHJLyTNQKJBoJCit5JWwSdtkDGa4KT",
    "new_uri": "https://dup-in-isolate.s3.us-west-1.amazonaws.com/1637-lock.json"
  },
  {
    "mint_account": "AN2ePJ1LeJMYWnrxK9zUh3yppNbhWy4b7rz5v9VuVGLb",
    "new_uri": "https://dup-in-isolate.s3.us-west-1.amazonaws.com/3543-lock.json"
  },
  {
    "mint_account": "3cEPvR3v1xfewmvSXCdidycnkJ84xph2N2vbBsd4Bahg",
    "new_uri": "https://dup-in-isolate.s3.us-west-1.amazonaws.com/3928-lock.json"
  },
  {
    "mint_account": "7nEECyLnyoXCaEtWw5YHRga2vg8PM6ttSsq3ZyhqNniy",
    "new_uri": "https://dup-in-isolate.s3.us-west-1.amazonaws.com/1650-lock.json"
  },
  {
    "mint_account": "EUTxApaXYRC255vtDjKcdwFxcLrq4KknDLxmaaaEmG5c",
    "new_uri": "https://dup-in-isolate.s3.us-west-1.amazonaws.com/3569-lock.json"
  },
  {
    "mint_account": "7T8A1ZQYAoGcXjTftqCEAYnakGHbNxKoUZVJDd1FNzsB",
    "new_uri": "https://dup-in-isolate.s3.us-west-1.amazonaws.com/1688-lock.json"
  },
  {
    "mint_account": "H84hTbRzpjyNkqmbgx2NYoPU2RiXpN2pyc83oj61XFVt",
    "new_uri": "https://dup-in-isolate.s3.us-west-1.amazonaws.com/1742-lock.json"
  },
  {
    "mint_account": "jHzuCNHggAn6nq5ocS6bSQ99QTdPVsJ96J4ww4rswrJ",
    "new_uri": "https://dup-in-isolate.s3.us-west-1.amazonaws.com/1743-lock.json"
  },
  {
    "mint_account": "DP9ZL44kMVfX7hLdeqHHNUoCnJLFLtcCqnrETpVA4rhW",
    "new_uri": "https://dup-in-isolate.s3.us-west-1.amazonaws.com/1699-lock.json"
  },
  {
    "mint_account": "367m3K2HeP2bPAecX7bL3zc648BAnqH85F98NoTNQdXU",
    "new_uri": "https://dup-in-isolate.s3.us-west-1.amazonaws.com/1757-lock.json"
  },
  {
    "mint_account": "DX9CowwaL4dgWoYWNgnNerNSFaPAQyUg9LPVCoHh5FbC",
    "new_uri": "https://dup-in-isolate.s3.us-west-1.amazonaws.com/1705-lock.json"
  },
  {
    "mint_account": "3gTEkE3HrK5JJBF6Rqd36tgrAFREWCj7zfabsnZuGJXW",
    "new_uri": "https://dup-in-isolate.s3.us-west-1.amazonaws.com/1756-lock.json"
  },
  {
    "mint_account": "d4ukLvSvdVp736omwewD85nqaqvgEJ5Cx2U6Pc2fLQu",
    "new_uri": "https://dup-in-isolate.s3.us-west-1.amazonaws.com/1759-lock.json"
  },
  {
    "mint_account": "3HK6FEH2N7iyphrCssubrdiQvVbSZVxrCahxQJEVspbM",
    "new_uri": "https://dup-in-isolate.s3.us-west-1.amazonaws.com/1710-lock.json"
  },
  {
    "mint_account": "E1oR5xGZK4mhQ2nDuvinsJwnjtksZu996ttqvTodwx99",
    "new_uri": "https://dup-in-isolate.s3.us-west-1.amazonaws.com/1709-lock.json"
  },
  {
    "mint_account": "AWbSzCx598aJampTvTaNhcJisngboa25UK6VhJMiUv4V",
    "new_uri": "https://dup-in-isolate.s3.us-west-1.amazonaws.com/1714-lock.json"
  },
  {
    "mint_account": "9DRYxWYBKCoknHJxeCwTmt4vu4w5sN5JWj3m27k1ys4T",
    "new_uri": "https://dup-in-isolate.s3.us-west-1.amazonaws.com/1794-lock.json"
  },
  {
    "mint_account": "5p5UQxpjNEF7Mak5D6FRYBMy45kPBvkCFqPVX9v1R2PU",
    "new_uri": "https://dup-in-isolate.s3.us-west-1.amazonaws.com/4007-lock.json"
  },
  {
    "mint_account": "A2LukEG5z576F6ot9hyzy9RJhz4xddtjHrj3UduGFMos",
    "new_uri": "https://dup-in-isolate.s3.us-west-1.amazonaws.com/1717-lock.json"
  },
  {
    "mint_account": "BwhNLepk3gU8tVA17CzEmkMCgm48rXW9P3knuZSRpXd5",
    "new_uri": "https://dup-in-isolate.s3.us-west-1.amazonaws.com/1770-lock.json"
  },
  {
    "mint_account": "9kQpLJFrRe46jyhVRgo8NYmSi22jcMesyjeh2Zffp17b",
    "new_uri": "https://dup-in-isolate.s3.us-west-1.amazonaws.com/1718-lock.json"
  },
  {
    "mint_account": "E9W6fV6JeCinb4CPypG63UaCoJcpgCShorPVixvV7cNG",
    "new_uri": "https://dup-in-isolate.s3.us-west-1.amazonaws.com/1771-lock.json"
  },
  {
    "mint_account": "53VTWHroo55MmNrD8sLYbPd8xNnX98p3WTFt1KbeZrcW",
    "new_uri": "https://dup-in-isolate.s3.us-west-1.amazonaws.com/1799-lock.json"
  },
  {
    "mint_account": "6LR2P5C9ypaunHHu4DZcjUd8k6Y9keXYgnLT4RtEkuN2",
    "new_uri": "https://dup-in-isolate.s3.us-west-1.amazonaws.com/1772-lock.json"
  },
  {
    "mint_account": "8T7Ftv7dXKEQFxBszixTXt3f6TN7sCfJyNnZHciqQdZH",
    "new_uri": "https://dup-in-isolate.s3.us-west-1.amazonaws.com/1720-lock.json"
  },
  {
    "mint_account": "77SzWSDBRVLJ2CQJgJ9XtJBRQR2fkz6BgGWBGN6yrMFQ",
    "new_uri": "https://dup-in-isolate.s3.us-west-1.amazonaws.com/1773-lock.json"
  },
  {
    "mint_account": "5iuvC1BqPJEZJG5xT2danKtQrNKi5aL2cnYk6Zcd7Zxe",
    "new_uri": "https://dup-in-isolate.s3.us-west-1.amazonaws.com/1803-lock.json"
  },
  {
    "mint_account": "HHfS7SuqkUJq5cmFFnZkRZhGM9hxnQdsJDy5ut2ahG2n",
    "new_uri": "https://dup-in-isolate.s3.us-west-1.amazonaws.com/1776-lock.json"
  },
  {
    "mint_account": "HX6VU7yuicZaseCjZDLPcWuafzAE6Lqxed2jp3igQ9B4",
    "new_uri": "https://dup-in-isolate.s3.us-west-1.amazonaws.com/1778-lock.json"
  },
  {
    "mint_account": "9xTbeQbggPHiNeBFrtaueFkbZEsfdTbdfjuLyFFd6BZ3",
    "new_uri": "https://dup-in-isolate.s3.us-west-1.amazonaws.com/1805-lock.json"
  },
  {
    "mint_account": "FM8NUza9PJQuaZ8Ju9wbSHDo7m4u8K9P8QsZ8pqw1mba",
    "new_uri": "https://dup-in-isolate.s3.us-west-1.amazonaws.com/1726-lock.json"
  },
  {
    "mint_account": "DRCZFFVY3BYZjtAWjv49dtcy8t1xcnuERwvBaE7XvtmY",
    "new_uri": "https://dup-in-isolate.s3.us-west-1.amazonaws.com/1806-lock.json"
  },
  {
    "mint_account": "FBiPwTC4Cz7AzGquPqd2j6KReLd96frmohK6eFvtmWpP",
    "new_uri": "https://dup-in-isolate.s3.us-west-1.amazonaws.com/1807-lock.json"
  },
  {
    "mint_account": "67YMvfqZnUxE622tZijZJzd1U7A8VfQiZhDKixFofZq9",
    "new_uri": "https://dup-in-isolate.s3.us-west-1.amazonaws.com/1780-lock.json"
  },
  {
    "mint_account": "8VjHb2a5ZKWfG32WfGRuQtbJbyD9NbauDG4ifN5ybJFQ",
    "new_uri": "https://dup-in-isolate.s3.us-west-1.amazonaws.com/1811-lock.json"
  },
  {
    "mint_account": "7198EsQEZkysuE4BbwonyUNuq4uUZkAhJsthbodn3N7",
    "new_uri": "https://dup-in-isolate.s3.us-west-1.amazonaws.com/1784-lock.json"
  },
  {
    "mint_account": "7RPPQvsfNwaqQGFRoVy1RMSUms8YZZTBLuDh6eWhfNWq",
    "new_uri": "https://dup-in-isolate.s3.us-west-1.amazonaws.com/1810-lock.json"
  },
  {
    "mint_account": "4UDyydH8haULV3nb1zjjq1ouisF5KFrcpvTBweSiNy17",
    "new_uri": "https://dup-in-isolate.s3.us-west-1.amazonaws.com/1730-lock.json"
  },
  {
    "mint_account": "93ff1Jh8YUKFvfeYvNx47HWSqzVHeFUeY2z5pev39byf",
    "new_uri": "https://dup-in-isolate.s3.us-west-1.amazonaws.com/1728-lock.json"
  },
  {
    "mint_account": "8MVLTRi8WJk557CjsR53yNzXHPvzuGRbAHZusYZj2JDG",
    "new_uri": "https://dup-in-isolate.s3.us-west-1.amazonaws.com/1808-lock.json"
  },
  {
    "mint_account": "BkkBBR53hYDxQHonhDjsT4RaU2z5yf2ddCdXeWLKGbCt",
    "new_uri": "https://dup-in-isolate.s3.us-west-1.amazonaws.com/1732-lock.json"
  },
  {
    "mint_account": "66p5BqAvPXSm7DfXNjyeEevnC9C7MeB3MejbsGVwAqkV",
    "new_uri": "https://dup-in-isolate.s3.us-west-1.amazonaws.com/1812-lock.json"
  },
  {
    "mint_account": "29xehaeimUrAaQJFHxgkEEZUnhd28rJ3WydtzTyoSgqq",
    "new_uri": "https://dup-in-isolate.s3.us-west-1.amazonaws.com/1816-lock.json"
  },
  {
    "mint_account": "96HzEnbqWhsuqHHywdDjftJ2C1pvycq3tU1NuY6kob5A",
    "new_uri": "https://dup-in-isolate.s3.us-west-1.amazonaws.com/1789-lock.json"
  },
  {
    "mint_account": "7n7MjE2mqXNU5epb1SQF9XqpHySMzFJTwoCjQeAdAsn9",
    "new_uri": "https://dup-in-isolate.s3.us-west-1.amazonaws.com/1817-lock.json"
  },
  {
    "mint_account": "6XCx4sTrLqWegzfwoMa1YHRySB1i6orD38kPTXhA3zJk",
    "new_uri": "https://dup-in-isolate.s3.us-west-1.amazonaws.com/1790-lock.json"
  },
  {
    "mint_account": "DeQTfNbEBoG7bMyN4LbQuGot44KsnZEeopzN2DL6itos",
    "new_uri": "https://dup-in-isolate.s3.us-west-1.amazonaws.com/1738-lock.json"
  },
  {
    "mint_account": "FCnrsDZzGB6voKGo9v8MJZcz3K2DMyp983kdjcZwD3LB",
    "new_uri": "https://dup-in-isolate.s3.us-west-1.amazonaws.com/1818-lock.json"
  },
  {
    "mint_account": "C6ZoGoEsM2TQMUcKkknYtc7MLjapjDJcUVTU7j4tpJPW",
    "new_uri": "https://dup-in-isolate.s3.us-west-1.amazonaws.com/4156-lock.json"
  },
  {
    "mint_account": "8NGycA4t4jppDcdvVuniRbRMWHLiJqVprjuLkrUhPzut",
    "new_uri": "https://dup-in-isolate.s3.us-west-1.amazonaws.com/3883-lock.json"
  },
  {
    "mint_account": "EKWH3KPC9PdBKjrUt4ChFHJM8w17i8B4kT4AqHj1DZk1",
    "new_uri": "https://dup-in-isolate.s3.us-west-1.amazonaws.com/3708-lock.json"
  },
  {
    "mint_account": "DN5HAyrroyei6Jv969o8iWSUELKjTDRtQawGB869rBTR",
    "new_uri": "https://dup-in-isolate.s3.us-west-1.amazonaws.com/3599-lock.json"
  },
  {
    "mint_account": "HFJkb4qSU6K3krxhDGAZyKEVivenL6zxuyhCv6YPjXQQ",
    "new_uri": "https://dup-in-isolate.s3.us-west-1.amazonaws.com/4188-lock.json"
  },
  {
    "mint_account": "DTYn2JznZ3on8v2szxR1bXuPUCwH1zFZChWnfKbDyMrh",
    "new_uri": "https://dup-in-isolate.s3.us-west-1.amazonaws.com/3961-lock.json"
  },
  {
    "mint_account": "5xgC51oTHpexqWiLh8Y1vLrP4vFaZpt6rYHBhfDktimm",
    "new_uri": "https://dup-in-isolate.s3.us-west-1.amazonaws.com/4028-lock.json"
  },
  {
    "mint_account": "67BBqNgkngpqU7yw8skZGW7i4wEE4ZaJX5NA1Y76P8k4",
    "new_uri": "https://dup-in-isolate.s3.us-west-1.amazonaws.com/3552-lock.json"
  },
  {
    "mint_account": "CwrH3Uzf2GWYwkUpaRXCsAcQgZEPycyJ1d9YhQmKxnYY",
    "new_uri": "https://dup-in-isolate.s3.us-west-1.amazonaws.com/3694-lock.json"
  },
  {
    "mint_account": "6ZmAVBh8fLfL7TMUpXVVzW1jGi1rGS6m6iUfACeYD7m",
    "new_uri": "https://dup-in-isolate.s3.us-west-1.amazonaws.com/3563-lock.json"
  },
  {
    "mint_account": "DkThQ1DRqPfBtG8hvAToin1E6jtvyJ7iSqSXYZUxXvYe",
    "new_uri": "https://dup-in-isolate.s3.us-west-1.amazonaws.com/3920-lock.json"
  },
  {
    "mint_account": "2NHi18J5GUcmvCzLj9TpJbziEKErRuvpXLvgFiyXyTsG",
    "new_uri": "https://dup-in-isolate.s3.us-west-1.amazonaws.com/3857-lock.json"
  },
  {
    "mint_account": "Fs7u4EU1SYQHDN7wwY6bDeMYiDjjsDVtWkWF7g6krP4V",
    "new_uri": "https://dup-in-isolate.s3.us-west-1.amazonaws.com/3915-lock.json"
  },
  {
    "mint_account": "7m22c7MoAzRBT2wvMWieXhrXNnxwKKW3hJtFXYrV5Qqt",
    "new_uri": "https://dup-in-isolate.s3.us-west-1.amazonaws.com/3612-lock.json"
  },
  {
    "mint_account": "HQg2NVyqhbu5ysy5HCxDfRshFmPXkYZdpenHGE4MFaCk",
    "new_uri": "https://dup-in-isolate.s3.us-west-1.amazonaws.com/4164-lock.json"
  },
  {
    "mint_account": "H4eAANSrjxDFKPz4E8kTKxDVcEe7cYku7tRTp4YnPvH7",
    "new_uri": "https://dup-in-isolate.s3.us-west-1.amazonaws.com/3919-lock.json"
  },
  {
    "mint_account": "EabtVT4A6E3bKhK4krjq7BvowNNkkp4QTnezYFf3KgF2",
    "new_uri": "https://dup-in-isolate.s3.us-west-1.amazonaws.com/3741-lock.json"
  },
  {
    "mint_account": "CnU2vnngRKLaAczgrBLfKmZHpVfq3s638EdgCzZGKJEQ",
    "new_uri": "https://dup-in-isolate.s3.us-west-1.amazonaws.com/3560-lock.json"
  },
  {
    "mint_account": "iS42kPPxQ8MFrTLQYHAMVpxH8LG3P1ciBEJDKfG6eTk",
    "new_uri": "https://dup-in-isolate.s3.us-west-1.amazonaws.com/3943-lock.json"
  },
  {
    "mint_account": "CcvcdaaGUWmuk3kLDo5gSGsVK6H4ztZ3NPUuby39kPaL",
    "new_uri": "https://dup-in-isolate.s3.us-west-1.amazonaws.com/4219-lock.json"
  },
  {
    "mint_account": "5GKfAybabjoJgiFoSTLTrkMYaPh3rUa9SDhKKDPb91DM",
    "new_uri": "https://dup-in-isolate.s3.us-west-1.amazonaws.com/3946-lock.json"
  },
  {
    "mint_account": "9H52E496EN5MFMZ3dEE6MVJGC25JfdoDPfKNhRsU9jBg",
    "new_uri": "https://dup-in-isolate.s3.us-west-1.amazonaws.com/4058-lock.json"
  },
  {
    "mint_account": "H8HK27VwnySPLepzYDgsBPwD6fsGY8ic9eC3PRm1SekK",
    "new_uri": "https://dup-in-isolate.s3.us-west-1.amazonaws.com/3779-lock.json"
  },
  {
    "mint_account": "HaSm51EYfH2YCxhYFLm9HcqWZd4AHHmLGXxVDUR5i3az",
    "new_uri": "https://dup-in-isolate.s3.us-west-1.amazonaws.com/3895-lock.json"
  },
  {
    "mint_account": "AL8jDr19Rrk79j6CBm7HhnGD6pXYLzQjzyy6dwhMgBUs",
    "new_uri": "https://dup-in-isolate.s3.us-west-1.amazonaws.com/4037-lock.json"
  },
  {
    "mint_account": "F1SrEq8aFvLZCF5Mjf1xfCh9epadgwT3dPYLZRbv6tvN",
    "new_uri": "https://dup-in-isolate.s3.us-west-1.amazonaws.com/3690-lock.json"
  },
  {
    "mint_account": "74eXhCZ1AK8Qq4YdVUGUtr5H6wQGewJrB9nwNVmpTZzv",
    "new_uri": "https://dup-in-isolate.s3.us-west-1.amazonaws.com/3703-lock.json"
  },
  {
    "mint_account": "FkfTZiJt1yEAssznAJtesqZcp7ppwgixd9VVMKc8hP3U",
    "new_uri": "https://dup-in-isolate.s3.us-west-1.amazonaws.com/3699-lock.json"
  },
  {
    "mint_account": "7E1kVvYv8S6VcXpNik855yPg88SUFy5EyJgpa3F4ZfWc",
    "new_uri": "https://dup-in-isolate.s3.us-west-1.amazonaws.com/3823-lock.json"
  },
  {
    "mint_account": "94MAquFLCH84yTS7fvSeDiFeWEgoqAfcATQmqDow6Lbx",
    "new_uri": "https://dup-in-isolate.s3.us-west-1.amazonaws.com/3784-lock.json"
  },
  {
    "mint_account": "GCsCZ7gRUpe7FuYT9o8d4soB8QWz6Fdp6fwBCKFMrFug",
    "new_uri": "https://dup-in-isolate.s3.us-west-1.amazonaws.com/3520-lock.json"
  },
  {
    "mint_account": "13TW18qqgenBMYLMei2a7d9hvCmRRAuB7tx4eRPB7mof",
    "new_uri": "https://dup-in-isolate.s3.us-west-1.amazonaws.com/3523-lock.json"
  },
  {
    "mint_account": "2bSiXeUZBT8uYkYgz6hwW4VkABazthsjHwL9qpdS3CWx",
    "new_uri": "https://dup-in-isolate.s3.us-west-1.amazonaws.com/3888-lock.json"
  },
  {
    "mint_account": "6kn2Rf2T1VVkwR31dStG59QZhwf7aXGSFVAqqqKAt2k3",
    "new_uri": "https://dup-in-isolate.s3.us-west-1.amazonaws.com/3524-lock.json"
  },
  {
    "mint_account": "DzH1DKwPGjXjH5g4Nria5Pucf9YqtLL8RN7jpLyfx6Yb",
    "new_uri": "https://dup-in-isolate.s3.us-west-1.amazonaws.com/3893-lock.json"
  },
  {
    "mint_account": "GovzN63xCqENczJcidkosqxEaJC6MTa1rjBE1ydg3b4j",
    "new_uri": "https://dup-in-isolate.s3.us-west-1.amazonaws.com/3525-lock.json"
  },
  {
    "mint_account": "EX9Bs98KCXYusAvgAauJXF8kFnJVEonqnZrJvjFpZxf7",
    "new_uri": "https://dup-in-isolate.s3.us-west-1.amazonaws.com/3528-lock.json"
  },
  {
    "mint_account": "3sid51KnGK1wnymGUZYsKqsibCAr6jVQivTTDEF9L9qh",
    "new_uri": "https://dup-in-isolate.s3.us-west-1.amazonaws.com/3896-lock.json"
  },
  {
    "mint_account": "DnypQtvDuZSXasNmHyHgaf5RH2E3CiTL3HH8ydUP5sn",
    "new_uri": "https://dup-in-isolate.s3.us-west-1.amazonaws.com/3531-lock.json"
  },
  {
    "mint_account": "4Yuz4ojvT57kSg1N76BqNu2rCU4nGBw98AHubPypErQz",
    "new_uri": "https://dup-in-isolate.s3.us-west-1.amazonaws.com/3534-lock.json"
  },
  {
    "mint_account": "B1uiBMXMyvJDwAPr1VBrnxsHizJ6vodYrWqKXJSmt42v",
    "new_uri": "https://dup-in-isolate.s3.us-west-1.amazonaws.com/3901-lock.json"
  },
  {
    "mint_account": "8LtmCGnmdckgk1vWKmYwraibWut8GmyXDF6Vj2DQPMKq",
    "new_uri": "https://dup-in-isolate.s3.us-west-1.amazonaws.com/3906-lock.json"
  },
  {
    "mint_account": "E6CcrjQMEBUsa7hy6skjfHXoEyot2HhF5PNkAtbJqU7d",
    "new_uri": "https://dup-in-isolate.s3.us-west-1.amazonaws.com/3904-lock.json"
  },
  {
    "mint_account": "88pd3jaZ7AAVujMkykg7ea6z2Mw8CVvZnsxE4fyLtBqz",
    "new_uri": "https://dup-in-isolate.s3.us-west-1.amazonaws.com/3544-lock.json"
  },
  {
    "mint_account": "F3q4hJ3ymxFq7ukoFwiPwCzg5bTD97z33k1fizUMp7NB",
    "new_uri": "https://dup-in-isolate.s3.us-west-1.amazonaws.com/3545-lock.json"
  },
  {
    "mint_account": "FhxgTwwJBeRriPkSxcpbqcgFL1hnquzVUPCii2YkrcEB",
    "new_uri": "https://dup-in-isolate.s3.us-west-1.amazonaws.com/3547-lock.json"
  },
  {
    "mint_account": "HYz5ihFmGAkK67qaiuqd7WV4GPy2xuYb1i6Yd1Kr9fu8",
    "new_uri": "https://dup-in-isolate.s3.us-west-1.amazonaws.com/3916-lock.json"
  },
  {
    "mint_account": "49URs86roCJmK7bSappH8iof37te8GJzKpKhB34XVWWE",
    "new_uri": "https://dup-in-isolate.s3.us-west-1.amazonaws.com/3551-lock.json"
  },
  {
    "mint_account": "GMPvWB5Hfs32uQeikNmkiuTRYSaT7n5miWJMjeXxUG6Z",
    "new_uri": "https://dup-in-isolate.s3.us-west-1.amazonaws.com/3914-lock.json"
  },
  {
    "mint_account": "XkzRuxwBuhU2P17twT87rNHsrGTh3KZtscvQdjk4sPB",
    "new_uri": "https://dup-in-isolate.s3.us-west-1.amazonaws.com/3922-lock.json"
  },
  {
    "mint_account": "EQn4cKhPFzB35eTLMAaLGSet7wZBpUTDnV6nzhMBMeGV",
    "new_uri": "https://dup-in-isolate.s3.us-west-1.amazonaws.com/3925-lock.json"
  },
  {
    "mint_account": "9ppkNvP2rgekxCitBnPu1f5DKc1W2fsJ5YLX7szJq31A",
    "new_uri": "https://dup-in-isolate.s3.us-west-1.amazonaws.com/3930-lock.json"
  },
  {
    "mint_account": "BUifsNPPyoLD7abfwyFFw4v42ySMxQjBsNQEbuftovre",
    "new_uri": "https://dup-in-isolate.s3.us-west-1.amazonaws.com/3933-lock.json"
  },
  {
    "mint_account": "5EnndQNE1bN6jwNNr3jvkY78jZQd54nKcu9e3AQZTXLg",
    "new_uri": "https://dup-in-isolate.s3.us-west-1.amazonaws.com/3932-lock.json"
  },
  {
    "mint_account": "EDVH1yYAfbkKd13aHJk97xNqPtqHHDrFgvbbYGdfzqRT",
    "new_uri": "https://dup-in-isolate.s3.us-west-1.amazonaws.com/3938-lock.json"
  },
  {
    "mint_account": "HcPSbQuaNL6AC4gWDJY1jAC19Pd9fPESQsj6FHGLMdoa",
    "new_uri": "https://dup-in-isolate.s3.us-west-1.amazonaws.com/3573-lock.json"
  },
  {
    "mint_account": "94z9CQNZ52SLzaYi159vwAWG1DPp7ZvuiHniiTaYzZ2g",
    "new_uri": "https://dup-in-isolate.s3.us-west-1.amazonaws.com/3578-lock.json"
  },
  {
    "mint_account": "DyEGzksxos1PbPpMvbb7jwyJQF4iJNAA84eHb5Ter8XZ",
    "new_uri": "https://dup-in-isolate.s3.us-west-1.amazonaws.com/3584-lock.json"
  },
  {
    "mint_account": "BoaGSN3VtctnqdJk9NhHWNtazTiAHR53YvMuj7LRTfCZ",
    "new_uri": "https://dup-in-isolate.s3.us-west-1.amazonaws.com/3586-lock.json"
  },
  {
    "mint_account": "GDi8tJp7rQnpopG83c55Dhwzjjs2KPKLEcD2zL38crYp",
    "new_uri": "https://dup-in-isolate.s3.us-west-1.amazonaws.com/3589-lock.json"
  },
  {
    "mint_account": "FCnseZRqCHLppGVWe3zG8LvSD7Pv1uwxdXEZMr9FR7oB",
    "new_uri": "https://dup-in-isolate.s3.us-west-1.amazonaws.com/3956-lock.json"
  },
  {
    "mint_account": "5UauHzSfbC3JiziiagU9AtFubRpPBtuhZpUYbsoCEzUV",
    "new_uri": "https://dup-in-isolate.s3.us-west-1.amazonaws.com/3738-lock.json"
  },
  {
    "mint_account": "3WFAAvFVoaiade3Bfkc27bZWtzT68zNMz27zjEr8JJV2",
    "new_uri": "https://dup-in-isolate.s3.us-west-1.amazonaws.com/3591-lock.json"
  },
  {
    "mint_account": "Bwv3odkucZ281kiwkPcnEJMZj954ZNF6yxGiez2pY85A",
    "new_uri": "https://dup-in-isolate.s3.us-west-1.amazonaws.com/3958-lock.json"
  },
  {
    "mint_account": "9E85LCjk8Eso4og5AiLhWMx3pGVLKR2UPzCadNLS7agq",
    "new_uri": "https://dup-in-isolate.s3.us-west-1.amazonaws.com/3546-lock.json"
  },
  {
    "mint_account": "GXQdY5ipbNgr4Vc4AciKrTgnc9yu6X1YiDsAdRtPGNEA",
    "new_uri": "https://dup-in-isolate.s3.us-west-1.amazonaws.com/3962-lock.json"
  },
  {
    "mint_account": "8x96oQADgfu8cakhrywfCxQkLHiiFWjuREoTP1PmJGV6",
    "new_uri": "https://dup-in-isolate.s3.us-west-1.amazonaws.com/3598-lock.json"
  },
  {
    "mint_account": "49gGR1mAec54eNPGYbduBDiw9DkFs2wgMScDuNnkY5UM",
    "new_uri": "https://dup-in-isolate.s3.us-west-1.amazonaws.com/3968-lock.json"
  },
  {
    "mint_account": "2JaKfvJYqoyFQyhSbSctp9sew7sjyjctrZZAW5tRn7Lb",
    "new_uri": "https://dup-in-isolate.s3.us-west-1.amazonaws.com/3967-lock.json"
  },
  {
    "mint_account": "EkYG811eCqb1Vvxw1veXTqB3WzGMXR9DR56eM1H83bXZ",
    "new_uri": "https://dup-in-isolate.s3.us-west-1.amazonaws.com/3969-lock.json"
  },
  {
    "mint_account": "FNyDFHaHMbGrcMH3drjmu3Z4PjimWWJGJNGZqGdky9uK",
    "new_uri": "https://dup-in-isolate.s3.us-west-1.amazonaws.com/3608-lock.json"
  },
  {
    "mint_account": "4c45mVv5aXHLVMTVENPKrn9BuJD9eFk4bMxDsumMNZnx",
    "new_uri": "https://dup-in-isolate.s3.us-west-1.amazonaws.com/3972-lock.json"
  },
  {
    "mint_account": "EdkdbgpxBQvsRmPUknWiAnF5UGbh5JTxVGjqfmoBayyn",
    "new_uri": "https://dup-in-isolate.s3.us-west-1.amazonaws.com/3980-lock.json"
  },
  {
    "mint_account": "C5jV6BPddLVQSYnZbohX9ZFVxb9ZRwmrUNKHzh9wsJE",
    "new_uri": "https://dup-in-isolate.s3.us-west-1.amazonaws.com/3977-lock.json"
  },
  {
    "mint_account": "2YiBva2WzGZZSdKgDPFNx52r8ETK7iS8U7sC72csyX6c",
    "new_uri": "https://dup-in-isolate.s3.us-west-1.amazonaws.com/3983-lock.json"
  },
  {
    "mint_account": "AgMQGYSjgeBYavNGTxDo9twVGaKQ7Z4ZACstvLtLdiMd",
    "new_uri": "https://dup-in-isolate.s3.us-west-1.amazonaws.com/3622-lock.json"
  },
  {
    "mint_account": "5Gp5NGkYDySHBRJDyLinKaeVodJjqnsbbByDGJREGEdz",
    "new_uri": "https://dup-in-isolate.s3.us-west-1.amazonaws.com/3623-lock.json"
  },
  {
    "mint_account": "CxxxSfgTCJjbZfDUQ57ZkAtFcSsGfFnjrUkLZgeH4Kzs",
    "new_uri": "https://dup-in-isolate.s3.us-west-1.amazonaws.com/3986-lock.json"
  },
  {
    "mint_account": "3wUjyuCLT9G966oHonSjDVktJRXt1p8mXa6GixETttSH",
    "new_uri": "https://dup-in-isolate.s3.us-west-1.amazonaws.com/3987-lock.json"
  },
  {
    "mint_account": "4oJLgJ77eY2P5y7PRDvoxQBb9WUuEM6eFG6TDtTjHU5G",
    "new_uri": "https://dup-in-isolate.s3.us-west-1.amazonaws.com/3625-lock.json"
  },
  {
    "mint_account": "o4nzTtqVAMydh5YqLd6AU2g3nCa3LhPdFTWLWBxJQy8",
    "new_uri": "https://dup-in-isolate.s3.us-west-1.amazonaws.com/3995-lock.json"
  },
  {
    "mint_account": "7PyYCFTMT44NFFhTxDMeSLN6M2i6HnnMxjkN4ujnQhvv",
    "new_uri": "https://dup-in-isolate.s3.us-west-1.amazonaws.com/3626-lock.json"
  },
  {
    "mint_account": "66aUDmUnMGDax7Ag3MnEE353prmLvYUYTZZw24GW47G8",
    "new_uri": "https://dup-in-isolate.s3.us-west-1.amazonaws.com/3994-lock.json"
  },
  {
    "mint_account": "Dx9XtGC2PqAjLvmmyRijzYQGbeEqCQ2HD6Fw7FhnqVe1",
    "new_uri": "https://dup-in-isolate.s3.us-west-1.amazonaws.com/3632-lock.json"
  },
  {
    "mint_account": "2UA6ZegmCWAfccFsiKzFWKsqWCHgeB47cXdntEh64i1c",
    "new_uri": "https://dup-in-isolate.s3.us-west-1.amazonaws.com/4002-lock.json"
  },
  {
    "mint_account": "FHb7s9EJhcTKPDw34QZFjijeE9whPR6LzDy4EU8nbH69",
    "new_uri": "https://dup-in-isolate.s3.us-west-1.amazonaws.com/3640-lock.json"
  },
  {
    "mint_account": "m8kkPbcu1aeuvMu5gvdKLUQZZnvQuaQ6zYPdcv71hur",
    "new_uri": "https://dup-in-isolate.s3.us-west-1.amazonaws.com/4005-lock.json"
  },
  {
    "mint_account": "DQScU6NBMoM5HdsM44j2ENacGP41R4FNpq2dwzWw19KQ",
    "new_uri": "https://dup-in-isolate.s3.us-west-1.amazonaws.com/4239-lock.json"
  },
  {
    "mint_account": "9YEKr9bPmhg3MVvu4v8C9iV6ueuw2rkzaGrDNXUYR2sv",
    "new_uri": "https://dup-in-isolate.s3.us-west-1.amazonaws.com/4010-lock.json"
  },
  {
    "mint_account": "5bKV3PKS78iB9xiqoVRKkQ7bmwpGAUN14hREjnCdCcvL",
    "new_uri": "https://dup-in-isolate.s3.us-west-1.amazonaws.com/4013-lock.json"
  },
  {
    "mint_account": "HU2tpztAfR7KRXZb2EYQ8nUxkXEKFjB9RvgZRkoorjpx",
    "new_uri": "https://dup-in-isolate.s3.us-west-1.amazonaws.com/4015-lock.json"
  },
  {
    "mint_account": "ELkEGVXhaarr7KwDiFSZq5VEL1aGVdWCKLmk5nDckGKX",
    "new_uri": "https://dup-in-isolate.s3.us-west-1.amazonaws.com/3650-lock.json"
  },
  {
    "mint_account": "HX5ujeB5PLFDugAffM1W8ECxo8BEHFDTQ59gPXAgzabk",
    "new_uri": "https://dup-in-isolate.s3.us-west-1.amazonaws.com/4018-lock.json"
  },
  {
    "mint_account": "7u9AjsmVFYTpeLnksfUpXyff6Znv8TJo62ZkwjVASVRM",
    "new_uri": "https://dup-in-isolate.s3.us-west-1.amazonaws.com/4019-lock.json"
  },
  {
    "mint_account": "61Jd3szcqafnMAtavRV2Fn979yLa7PSXG1bxyEJB1xmo",
    "new_uri": "https://dup-in-isolate.s3.us-west-1.amazonaws.com/4023-lock.json"
  },
  {
    "mint_account": "FYczLLRyGqHN1LRLvMx8K8r62TbkiHvXPB9PherNDyt9",
    "new_uri": "https://dup-in-isolate.s3.us-west-1.amazonaws.com/3663-lock.json"
  },
  {
    "mint_account": "7s6sSNGs9jcS5HseqfvCPGy2mQCEPe1ieFRmaH9Z7Zft",
    "new_uri": "https://dup-in-isolate.s3.us-west-1.amazonaws.com/4030-lock.json"
  },
  {
    "mint_account": "Bw3R7wvK3cD7y5eg3h22iZHr9V9HPjFDqwRpih6ekqvN",
    "new_uri": "https://dup-in-isolate.s3.us-west-1.amazonaws.com/4034-lock.json"
  },
  {
    "mint_account": "Fa5exCZ6uS5exyGATTrw5fvits4QDqjq1xVCnpd7CrVz",
    "new_uri": "https://dup-in-isolate.s3.us-west-1.amazonaws.com/4033-lock.json"
  },
  {
    "mint_account": "CdRqnZfpAygvAaGjiiMHnwEeXZSXgKHWjRETAf6bJrVx",
    "new_uri": "https://dup-in-isolate.s3.us-west-1.amazonaws.com/3677-lock.json"
  },
  {
    "mint_account": "HQPg5rZRGXrbM3gZXPzJU1x2LCBTghtWL7Pr359XgmFH",
    "new_uri": "https://dup-in-isolate.s3.us-west-1.amazonaws.com/3673-lock.json"
  },
  {
    "mint_account": "AyYftCgXwbdW5WmgZhnEDZrxSYvHHG3hjA4m44wB6VQ6",
    "new_uri": "https://dup-in-isolate.s3.us-west-1.amazonaws.com/3676-lock.json"
  },
  {
    "mint_account": "3ozeER8maTS5yFtta1CsjqArbFC5BhAfkVR5UXvqXbAB",
    "new_uri": "https://dup-in-isolate.s3.us-west-1.amazonaws.com/4044-lock.json"
  },
  {
    "mint_account": "EskTmSUf9L5tkrX3tjQ1Ud611d2ig8mGSumBjGMMuG2y",
    "new_uri": "https://dup-in-isolate.s3.us-west-1.amazonaws.com/3680-lock.json"
  },
  {
    "mint_account": "9QuKuVAKE2Nh4RMrAU7Va2oSmF3YCqjbbcv3fXSdvjAe",
    "new_uri": "https://dup-in-isolate.s3.us-west-1.amazonaws.com/3679-lock.json"
  },
  {
    "mint_account": "7zr6jvu3vUQKwieiEZMGy3CcM5x1xwPD22HJCy2h4P75",
    "new_uri": "https://dup-in-isolate.s3.us-west-1.amazonaws.com/3682-lock.json"
  },
  {
    "mint_account": "DXWcRS1i9FVCio56wocuLHbi2SbhAuFWfrZfLzEUMDiD",
    "new_uri": "https://dup-in-isolate.s3.us-west-1.amazonaws.com/3683-lock.json"
  },
  {
    "mint_account": "7cCtZ6x7R82PDxuAJxEtNAXSmQqn4X2rjPV96kKuafd9",
    "new_uri": "https://dup-in-isolate.s3.us-west-1.amazonaws.com/3688-lock.json"
  },
  {
    "mint_account": "4ebbt4Qp7t4jqs5PMVXq2wmb2sKEoQt8C7mTxMg2muLZ",
    "new_uri": "https://dup-in-isolate.s3.us-west-1.amazonaws.com/3696-lock.json"
  },
  {
    "mint_account": "EhLQkX1W59yp1MaFvt69K54SUgJAHGUaSZjM1KvfCFuC",
    "new_uri": "https://dup-in-isolate.s3.us-west-1.amazonaws.com/4064-lock.json"
  },
  {
    "mint_account": "HrEVTR3jK8XasD2aroxkvfQMvtAPjCC7TWSdXGr8fdWk",
    "new_uri": "https://dup-in-isolate.s3.us-west-1.amazonaws.com/4066-lock.json"
  },
  {
    "mint_account": "8AmBHcr7wivWnNTcWGK4bL6hEmvWYaa5PMQnaCqoMPMe",
    "new_uri": "https://dup-in-isolate.s3.us-west-1.amazonaws.com/4068-lock.json"
  },
  {
    "mint_account": "AXrKQvQYn93rhqms6LQQSj3p5WM3inydpk7d4Wqw3iJD",
    "new_uri": "https://dup-in-isolate.s3.us-west-1.amazonaws.com/4075-lock.json"
  },
  {
    "mint_account": "5zLP2kV2UNhdhKcFNzxs4v1R7k4JHLkokMD6Pcrxh1H9",
    "new_uri": "https://dup-in-isolate.s3.us-west-1.amazonaws.com/3710-lock.json"
  },
  {
    "mint_account": "GFGSfUDJbpnB9vttmtbWbYtHYiQxVPyWDdT6AsGaz9up",
    "new_uri": "https://dup-in-isolate.s3.us-west-1.amazonaws.com/4077-lock.json"
  },
  {
    "mint_account": "ConPnUGEgTkfpSuiAdmt4RpmpjBeizpipoBVWij8qrwb",
    "new_uri": "https://dup-in-isolate.s3.us-west-1.amazonaws.com/3713-lock.json"
  },
  {
    "mint_account": "4PASPXnPjJdcjqqfiPVxz9JCPA91T29J7FyDTWWczfiE",
    "new_uri": "https://dup-in-isolate.s3.us-west-1.amazonaws.com/4081-lock.json"
  },
  {
    "mint_account": "Aisv9kZEoDV4jxRMza2F7sVS1Fxujzd3NHBTSsE3geCo",
    "new_uri": "https://dup-in-isolate.s3.us-west-1.amazonaws.com/3719-lock.json"
  },
  {
    "mint_account": "3s7qy1TzgzSinvacWCmmNa19t3y9zPgjnV31RpYGq2Mi",
    "new_uri": "https://dup-in-isolate.s3.us-west-1.amazonaws.com/4086-lock.json"
  },
  {
    "mint_account": "AfyZZwxJ4F79R6Tg3ySTbpdZw3XfR5AjS5eK8Jycem98",
    "new_uri": "https://dup-in-isolate.s3.us-west-1.amazonaws.com/3721-lock.json"
  },
  {
    "mint_account": "Dgzggoi2N1s3XRdhm1gwu7mUSgsoXK1t5DMWkGr3n6iM",
    "new_uri": "https://dup-in-isolate.s3.us-west-1.amazonaws.com/4092-lock.json"
  },
  {
    "mint_account": "Hh2LPBuodLpYLmGgfHgp7YAXgrAQ8wAeJzZtjaHGwj1B",
    "new_uri": "https://dup-in-isolate.s3.us-west-1.amazonaws.com/4090-lock.json"
  },
  {
    "mint_account": "6VF73Gk5q8LuvEQxp16NwJzL49jZhojCkRn8h1aidNG4",
    "new_uri": "https://dup-in-isolate.s3.us-west-1.amazonaws.com/3727-lock.json"
  },
  {
    "mint_account": "8PYNSKmAPjrYi4N3NXXAbLEoVoWJTsrCTA5zXfVm8KJi",
    "new_uri": "https://dup-in-isolate.s3.us-west-1.amazonaws.com/3729-lock.json"
  },
  {
    "mint_account": "6ujYwfVrzwwhLebJe59tUbmQSnqGviGwUpqLzvwj6Hob",
    "new_uri": "https://dup-in-isolate.s3.us-west-1.amazonaws.com/4094-lock.json"
  },
  {
    "mint_account": "8CpSUEZmh4xA6JpQty9X9GtpWhkQsjjG9JFuWDMAuBPT",
    "new_uri": "https://dup-in-isolate.s3.us-west-1.amazonaws.com/3730-lock.json"
  },
  {
    "mint_account": "3bMZLQWXEB98qmWvXnVwU1z3RbYvpUio8u4bm75DNgPc",
    "new_uri": "https://dup-in-isolate.s3.us-west-1.amazonaws.com/3731-lock.json"
  },
  {
    "mint_account": "Cyi6ueft1zBdSB422oi276GhZsDiDKMwJnqqwMbjKBd7",
    "new_uri": "https://dup-in-isolate.s3.us-west-1.amazonaws.com/4101-lock.json"
  },
  {
    "mint_account": "2YkDzsfTAFHveGdvFCA6S9n9zieHUju1XaWUT68E5ML7",
    "new_uri": "https://dup-in-isolate.s3.us-west-1.amazonaws.com/4105-lock.json"
  },
  {
    "mint_account": "4kpVSDpYinJDTQmCuMg5PFAuX33H9SH9Dv2AZPbacFtR",
    "new_uri": "https://dup-in-isolate.s3.us-west-1.amazonaws.com/4106-lock.json"
  },
  {
    "mint_account": "F8yjVX5gMr6DVgDFmTxU1YuvgeX6sXwEfr4jTx6BJF3b",
    "new_uri": "https://dup-in-isolate.s3.us-west-1.amazonaws.com/3882-lock.json"
  },
  {
    "mint_account": "5dbsuSJntWRzb1usQtfanhjefLMfoKLM3G5vAGBZKRWx",
    "new_uri": "https://dup-in-isolate.s3.us-west-1.amazonaws.com/4109-lock.json"
  },
  {
    "mint_account": "FZjChFWsqzqXKqGMXog2fWx6sLzHs7uPKytiNhWt78ZE",
    "new_uri": "https://dup-in-isolate.s3.us-west-1.amazonaws.com/4110-lock.json"
  },
  {
    "mint_account": "C7xrKWyFAbLj1fapUaA5g5MvTvNGCspvZszvEEyQ8Hwq",
    "new_uri": "https://dup-in-isolate.s3.us-west-1.amazonaws.com/3758-lock.json"
  },
  {
    "mint_account": "FyJA7ZMtYiVNzA9VazD5bWayFK9yy7WU2vX1smvRggfJ",
    "new_uri": "https://dup-in-isolate.s3.us-west-1.amazonaws.com/4247-lock.json"
  },
  {
    "mint_account": "3cNXkncVJerDUD8uGmZ53fT3hMC6YWCntGu74nVbiaYe",
    "new_uri": "https://dup-in-isolate.s3.us-west-1.amazonaws.com/4111-lock.json"
  },
  {
    "mint_account": "HoyB4EKUAXbr6WzFZr4BwQYU5NN9N6Y7aJYeQ83u7YjD",
    "new_uri": "https://dup-in-isolate.s3.us-west-1.amazonaws.com/4114-lock.json"
  },
  {
    "mint_account": "GyQofotimBe62Kn4WbyniuXnwgLZb6Kf9Hp7dGWW9KHd",
    "new_uri": "https://dup-in-isolate.s3.us-west-1.amazonaws.com/3752-lock.json"
  },
  {
    "mint_account": "BRUqyh4w5UL19fFCbEtcMpG1hcppWoRLtfWBURCeVUpy",
    "new_uri": "https://dup-in-isolate.s3.us-west-1.amazonaws.com/3753-lock.json"
  },
  {
    "mint_account": "FUi7NZkS2qGdDJySMHb3yB5xTy5YLKHx8rg4rbfg6WZS",
    "new_uri": "https://dup-in-isolate.s3.us-west-1.amazonaws.com/4129-lock.json"
  },
  {
    "mint_account": "CBAQ5QfAQRpikJfPyKAoksjRx6XQCugkniKWUzXMasVh",
    "new_uri": "https://dup-in-isolate.s3.us-west-1.amazonaws.com/4128-lock.json"
  },
  {
    "mint_account": "955r3ZwcbWZsoXqbv5QyU9Ht4uTUcJPKZAVY5a7LMtCi",
    "new_uri": "https://dup-in-isolate.s3.us-west-1.amazonaws.com/3761-lock.json"
  },
  {
    "mint_account": "BhABzBU3qJMgR9GgMCekHsP8MHpVqy838S1rcPcLhe3U",
    "new_uri": "https://dup-in-isolate.s3.us-west-1.amazonaws.com/3766-lock.json"
  },
  {
    "mint_account": "A1KwJK67tN2v1Sw3o717V7m6TfGyeAiP7xeyxiEbLPvL",
    "new_uri": "https://dup-in-isolate.s3.us-west-1.amazonaws.com/3765-lock.json"
  },
  {
    "mint_account": "F6Es21pGT3GjdvTm24HW8ZFuqvPymdBgYCZFkQ6sQkRi",
    "new_uri": "https://dup-in-isolate.s3.us-west-1.amazonaws.com/3767-lock.json"
  },
  {
    "mint_account": "9vwzK8111Fq2W8zE3Mn5BBdjmTnVVMXVV21beLKiaH8U",
    "new_uri": "https://dup-in-isolate.s3.us-west-1.amazonaws.com/4135-lock.json"
  },
  {
    "mint_account": "8iJa8Ghty1Y2eSiRPi6ScZEgmYvCCvJ2LHvWzGcuZhHZ",
    "new_uri": "https://dup-in-isolate.s3.us-west-1.amazonaws.com/4141-lock.json"
  },
  {
    "mint_account": "5ZdYKAaCvLF217AReZTqsdPNALjTzttWZqgkw74wQ2Ry",
    "new_uri": "https://dup-in-isolate.s3.us-west-1.amazonaws.com/3773-lock.json"
  },
  {
    "mint_account": "A1NjwzLexaEA53fJozUdRUr9wMasg3VJDdoM8X9bvTg1",
    "new_uri": "https://dup-in-isolate.s3.us-west-1.amazonaws.com/4143-lock.json"
  },
  {
    "mint_account": "7TDudRpiQbUN9aFWoTx1n6ujx4ihSijxzS4ZY5fTwyhX",
    "new_uri": "https://dup-in-isolate.s3.us-west-1.amazonaws.com/4147-lock.json"
  },
  {
    "mint_account": "DZoeryyFQbNYpRkujj1pXLxsbsHTW78jwL1YVvt7JzB2",
    "new_uri": "https://dup-in-isolate.s3.us-west-1.amazonaws.com/4177-lock.json"
  },
  {
    "mint_account": "BtaFQ3tbiLHygEhuZrCw2cNsVdiAMAxPHitWDTgSzxLL",
    "new_uri": "https://dup-in-isolate.s3.us-west-1.amazonaws.com/3778-lock.json"
  },
  {
    "mint_account": "DzkncXStmXEikwT5kxbxVJxCvmioGGeiZ64MJmARyUGe",
    "new_uri": "https://dup-in-isolate.s3.us-west-1.amazonaws.com/4148-lock.json"
  },
  {
    "mint_account": "6EWzhYBwGBMpRp4zDhdeeciCDHmZoxgwkmMNtukWBbVg",
    "new_uri": "https://dup-in-isolate.s3.us-west-1.amazonaws.com/3788-lock.json"
  },
  {
    "mint_account": "8kLSmtBwthmZYjqS62eAMQ74SpGTTeCe2TayxjvZiCg1",
    "new_uri": "https://dup-in-isolate.s3.us-west-1.amazonaws.com/3791-lock.json"
  },
  {
    "mint_account": "EqP1cZWKLbmKVWVcBJSt4raxGWJrCVMPwnvukpGV3NJR",
    "new_uri": "https://dup-in-isolate.s3.us-west-1.amazonaws.com/4160-lock.json"
  },
  {
    "mint_account": "8DAit6zkVfrt2n9bKa7FHJdAVdzxd4PntGeRNeCzAjvb",
    "new_uri": "https://dup-in-isolate.s3.us-west-1.amazonaws.com/3796-lock.json"
  },
  {
    "mint_account": "53CEHYxfdj47NW8d6MkRKCUWiGayDMZ2iUKbv2weA5GH",
    "new_uri": "https://dup-in-isolate.s3.us-west-1.amazonaws.com/4168-lock.json"
  },
  {
    "mint_account": "7PocPTv2gLxNn3JJWn5D4KzMjRJD8HWvZwvS6bYU7SYS",
    "new_uri": "https://dup-in-isolate.s3.us-west-1.amazonaws.com/4171-lock.json"
  },
  {
    "mint_account": "2kFS4dQKvTQMHyVJSDpp92Lq3FY7B8jWXkuLXjtWdXzq",
    "new_uri": "https://dup-in-isolate.s3.us-west-1.amazonaws.com/3809-lock.json"
  },
  {
    "mint_account": "2SjciGkfP4ySWmsr2BEJCcY3JhP4moxsRLFR7DLxMV3b",
    "new_uri": "https://dup-in-isolate.s3.us-west-1.amazonaws.com/3835-lock.json"
  },
  {
    "mint_account": "5tQt94j9edh3Ai8HjEoFEvC2sTn4iMJRSzGQG1bkzM9u",
    "new_uri": "https://dup-in-isolate.s3.us-west-1.amazonaws.com/4179-lock.json"
  },
  {
    "mint_account": "F2P1beE9EaQecVTCrEeM5FDXRjKXVxTo7qcPhFXReHrf",
    "new_uri": "https://dup-in-isolate.s3.us-west-1.amazonaws.com/4185-lock.json"
  },
  {
    "mint_account": "72kPbLeAmTvCAxNKt8sW3SLeQqsvm8BN7M4yLj581RMd",
    "new_uri": "https://dup-in-isolate.s3.us-west-1.amazonaws.com/3825-lock.json"
  },
  {
    "mint_account": "8P62acHt7EzRzDhmBa58HBfAyQd7rZTqZoupYSfdDcmo",
    "new_uri": "https://dup-in-isolate.s3.us-west-1.amazonaws.com/3844-lock.json"
  },
  {
    "mint_account": "bW4xLv528FCrVMxw5CeYERCtCiMioeb4vjYWVBcbGyL",
    "new_uri": "https://dup-in-isolate.s3.us-west-1.amazonaws.com/3829-lock.json"
  },
  {
    "mint_account": "86EiLCN6jf8aq7oAhR3eKzyc4JcaLfRF3mYp6kNrc3HR",
    "new_uri": "https://dup-in-isolate.s3.us-west-1.amazonaws.com/4193-lock.json"
  },
  {
    "mint_account": "DdeptWTefjJtHear1qniGt3865eFUBqmi9kodeogDiYQ",
    "new_uri": "https://dup-in-isolate.s3.us-west-1.amazonaws.com/4196-lock.json"
  },
  {
    "mint_account": "HTMHu1HnKwmui5ketDwpiA6ShApFZA7ExofvAXTzjLDA",
    "new_uri": "https://dup-in-isolate.s3.us-west-1.amazonaws.com/4197-lock.json"
  },
  {
    "mint_account": "sNHvp6r7mANstntYjqEgNjNi7tMA8LbUBFeRoKof4Tp",
    "new_uri": "https://dup-in-isolate.s3.us-west-1.amazonaws.com/4198-lock.json"
  },
  {
    "mint_account": "8todkXVdpb46wPx5V4um4jrJe7oR7q9qw3jHadQModxX",
    "new_uri": "https://dup-in-isolate.s3.us-west-1.amazonaws.com/3833-lock.json"
  },
  {
    "mint_account": "9ncJgmqpMpZ5fW5NutEU4tKdMZvX9ufquWxFyzsKNTYQ",
    "new_uri": "https://dup-in-isolate.s3.us-west-1.amazonaws.com/3838-lock.json"
  },
  {
    "mint_account": "AoDHGET5idFCpwqqL8SosqLx9tCimGsxueetnedsFvQT",
    "new_uri": "https://dup-in-isolate.s3.us-west-1.amazonaws.com/4227-lock.json"
  },
  {
    "mint_account": "BjPZFLE42UoYsbbTcxMtafu9gxta942riZgMwHxopgK7",
    "new_uri": "https://dup-in-isolate.s3.us-west-1.amazonaws.com/3841-lock.json"
  },
  {
    "mint_account": "2didnaiqdCUFU9W2owPasTWpP7fNVdrp7nL9CQhikSxd",
    "new_uri": "https://dup-in-isolate.s3.us-west-1.amazonaws.com/4208-lock.json"
  },
  {
    "mint_account": "2iKNGpQY6rxNgv8LavVjL5PH34RYbo4hpqueTCFQ8jjo",
    "new_uri": "https://dup-in-isolate.s3.us-west-1.amazonaws.com/3845-lock.json"
  },
  {
    "mint_account": "E6GPdJb8nhWspUyjKskbmKP32WPVcGQfDotzK2xoh3AV",
    "new_uri": "https://dup-in-isolate.s3.us-west-1.amazonaws.com/4212-lock.json"
  },
  {
    "mint_account": "Gxt31E37YWq6LyYhqyMpk8oauwj2tR9GKKxB1pDpJq82",
    "new_uri": "https://dup-in-isolate.s3.us-west-1.amazonaws.com/3850-lock.json"
  },
  {
    "mint_account": "7FEnMdin8L8u8sARBeqvQNPY51NGgL9ZWQCkWd5WRur1",
    "new_uri": "https://dup-in-isolate.s3.us-west-1.amazonaws.com/3858-lock.json"
  },
  {
    "mint_account": "4jaMW7FUcy3VkL8BFU6Xb7jr4PLmUV2u5e6o9fAaRsbt",
    "new_uri": "https://dup-in-isolate.s3.us-west-1.amazonaws.com/3859-lock.json"
  },
  {
    "mint_account": "5V4PCRBoHJBygwnwvyCkos6gVeW1DHF8hRruXdkjNuuf",
    "new_uri": "https://dup-in-isolate.s3.us-west-1.amazonaws.com/4235-lock.json"
  },
  {
    "mint_account": "Bv714DSsdNbZa2E6iVX4AQkPVjPgUTeTuJNsfmfkqyZC",
    "new_uri": "https://dup-in-isolate.s3.us-west-1.amazonaws.com/4233-lock.json"
  },
  {
    "mint_account": "3VdYwgnMoQmYtTV7xArNqZsLgjacTTw3oZPPaByx6E2J",
    "new_uri": "https://dup-in-isolate.s3.us-west-1.amazonaws.com/3874-lock.json"
  },
  {
    "mint_account": "36rnYJcGmxqDsWU9VZVetmxccTmMUkeamZSxyJZzVPnQ",
    "new_uri": "https://dup-in-isolate.s3.us-west-1.amazonaws.com/4238-lock.json"
  },
  {
    "mint_account": "yR79YYTUdTFvs4jYPm2pq5akwLrfHSZ3osp1cLAN2vk",
    "new_uri": "https://dup-in-isolate.s3.us-west-1.amazonaws.com/3877-lock.json"
  },
  {
    "mint_account": "DcEbTq6MwvNWT219sgahbEo4yV6zpyG3kYPEH1EDE3uz",
    "new_uri": "https://dup-in-isolate.s3.us-west-1.amazonaws.com/3876-lock.json"
  }
]
